{
   "agent": "RatchetRFC/0.1.0",
   "behavior": "OK",
   "behaviorClose": "OK",
   "case": 331,
   "closedByMe": true,
   "createStats": true,
   "createWirelog": true,
   "description": "Send 1000 compressed messages each of payload size 131072, auto-fragment to 0 octets. Use default permessage-deflate offer.",
   "droppedByMe": false,
   "duration": 17220,
   "expectation": "Receive echo'ed messages (with payload as sent). Timeout case after 480 secs.",
   "expected": {},
   "expectedClose": {
      "closeCode": [
         1000
      ],
      "closedByMe": true,
      "requireClean": true
   },
   "failedByMe": false,
   "httpRequest": "GET / HTTP/1.1\r\nUser-Agent: AutobahnTestSuite/0.8.0-0.10.9\r\nHost: host.ratchet.internal:9001\r\nUpgrade: WebSocket\r\nConnection: Upgrade\r\nPragma: no-cache\r\nCache-Control: no-cache\r\nSec-WebSocket-Key: NuPQqrMiI6Uu+aSQv/HqCQ==\r\nSec-WebSocket-Extensions: permessage-deflate; client_no_context_takeover; client_max_window_bits\r\nSec-WebSocket-Version: 13\r\n\r\n",
   "httpResponse": "HTTP/1.1 101 Switching Protocols\r\nUpgrade: websocket\r\nConnection: Upgrade\r\nSec-WebSocket-Accept: tt2rBzF1qrj0OoHQD6URQILeRsU=\r\nX-Powered-By: Ratchet\r\nSec-Websocket-Extensions: permessage-deflate; client_no_context_takeover\r\nContent-Length: 0\r\n\r\n",
   "id": "12.2.10",
   "isServer": false,
   "localCloseCode": 1000,
   "localCloseReason": null,
   "received": [],
   "remoteCloseCode": 1000,
   "remoteCloseReason": null,
   "reportCompressionRatio": true,
   "reportTime": true,
   "result": "Ok, received all echo'ed messages in time.",
   "resultClose": "Connection was properly closed",
   "rxFrameStats": {
      "2": 1000,
      "8": 1
   },
   "rxOctetStats": {
      "3": 1,
      "4": 1,
      "9": 1,
      "40": 1,
      "53": 1,
      "69": 1,
      "80": 1,
      "88": 1,
      "125": 1,
      "127": 1,
      "173": 1,
      "200": 1,
      "245": 1,
      "274": 1,
      "280": 1,
      "299": 1,
      "321": 1,
      "392": 2,
      "399": 1,
      "425": 1,
      "449": 1,
      "454": 1,
      "468": 1,
      "474": 1,
      "487": 1,
      "509": 1,
      "514": 1,
      "570": 1,
      "598": 1,
      "653": 1,
      "686": 1,
      "775": 1,
      "788": 1,
      "862": 1,
      "874": 1,
      "883": 1,
      "884": 1,
      "917": 1,
      "922": 1,
      "934": 1,
      "935": 1,
      "952": 1,
      "987": 1,
      "1012": 1,
      "1063": 1,
      "1075": 1,
      "1081": 1,
      "1104": 1,
      "1105": 1,
      "1120": 1,
      "1166": 1,
      "1172": 1,
      "1181": 1,
      "1208": 1,
      "1227": 1,
      "1250": 1,
      "1309": 1,
      "1328": 1,
      "1336": 1,
      "1349": 1,
      "1352": 1,
      "1355": 1,
      "1384": 1,
      "1433": 1,
      "1460": 28,
      "1462": 1,
      "1463": 1,
      "1473": 1,
      "1512": 1,
      "1514": 1,
      "1540": 2,
      "1600": 1,
      "1622": 1,
      "1635": 1,
      "1639": 1,
      "1670": 1,
      "1753": 1,
      "1768": 1,
      "1770": 1,
      "1776": 1,
      "1777": 1,
      "1808": 1,
      "1841": 1,
      "1844": 1,
      "1868": 1,
      "1896": 1,
      "1906": 1,
      "1957": 1,
      "1963": 1,
      "1979": 1,
      "1987": 1,
      "1994": 1,
      "1996": 1,
      "2005": 1,
      "2008": 1,
      "2021": 1,
      "2026": 1,
      "2066": 1,
      "2089": 1,
      "2096": 1,
      "2103": 1,
      "2119": 1,
      "2123": 1,
      "2131": 1,
      "2132": 1,
      "2137": 1,
      "2166": 1,
      "2205": 1,
      "2223": 1,
      "2245": 1,
      "2252": 1,
      "2259": 1,
      "2329": 1,
      "2340": 1,
      "2375": 1,
      "2384": 1,
      "2387": 1,
      "2406": 1,
      "2408": 1,
      "2409": 1,
      "2411": 1,
      "2430": 2,
      "2441": 1,
      "2456": 1,
      "2457": 1,
      "2497": 1,
      "2500": 1,
      "2517": 1,
      "2521": 1,
      "2551": 1,
      "2559": 1,
      "2587": 1,
      "2596": 1,
      "2604": 1,
      "2607": 1,
      "2612": 2,
      "2624": 1,
      "2647": 1,
      "2655": 1,
      "2685": 1,
      "2687": 1,
      "2703": 1,
      "2709": 1,
      "2715": 1,
      "2739": 1,
      "2742": 1,
      "2751": 1,
      "2755": 1,
      "2756": 2,
      "2762": 1,
      "2764": 1,
      "2769": 1,
      "2771": 1,
      "2797": 1,
      "2812": 1,
      "2834": 1,
      "2853": 1,
      "2876": 1,
      "2920": 37,
      "2923": 1,
      "2936": 1,
      "2948": 1,
      "2955": 1,
      "2968": 1,
      "2970": 1,
      "3023": 1,
      "3032": 1,
      "3042": 1,
      "3054": 1,
      "3108": 1,
      "3129": 1,
      "3141": 1,
      "3174": 1,
      "3183": 1,
      "3185": 1,
      "3202": 1,
      "3245": 1,
      "3265": 1,
      "3318": 1,
      "3340": 1,
      "3341": 1,
      "3349": 1,
      "3358": 1,
      "3389": 1,
      "3423": 1,
      "3453": 1,
      "3465": 1,
      "3469": 1,
      "3481": 1,
      "3484": 1,
      "3561": 1,
      "3577": 1,
      "3581": 1,
      "3620": 1,
      "3630": 1,
      "3657": 1,
      "3675": 1,
      "3682": 1,
      "3690": 1,
      "3745": 1,
      "3792": 1,
      "3804": 1,
      "3833": 1,
      "3841": 1,
      "3883": 1,
      "3892": 1,
      "3929": 1,
      "3934": 1,
      "3938": 1,
      "3948": 1,
      "3950": 1,
      "3951": 1,
      "3989": 1,
      "3996": 1,
      "3997": 1,
      "4004": 1,
      "4055": 1,
      "4056": 1,
      "4064": 1,
      "4072": 1,
      "4078": 1,
      "4085": 1,
      "4113": 1,
      "4128": 1,
      "4132": 1,
      "4161": 1,
      "4169": 1,
      "4174": 1,
      "4184": 1,
      "4216": 7,
      "4220": 1,
      "4256": 1,
      "4269": 1,
      "4285": 1,
      "4298": 1,
      "4304": 1,
      "4315": 1,
      "4379": 1,
      "4380": 59,
      "4385": 1,
      "4394": 1,
      "4404": 2,
      "4413": 1,
      "4414": 1,
      "4420": 1,
      "4448": 1,
      "4472": 1,
      "4518": 1,
      "4524": 1,
      "4567": 1,
      "4633": 1,
      "4639": 1,
      "4641": 1,
      "4643": 1,
      "4644": 1,
      "4658": 1,
      "4685": 1,
      "4688": 1,
      "4708": 1,
      "4711": 1,
      "4715": 1,
      "4735": 1,
      "4752": 1,
      "4788": 1,
      "4796": 1,
      "4816": 1,
      "4821": 1,
      "4823": 1,
      "4834": 1,
      "4857": 1,
      "4880": 1,
      "4916": 1,
      "4935": 1,
      "4945": 1,
      "4950": 1,
      "4993": 1,
      "5012": 1,
      "5037": 1,
      "5058": 1,
      "5060": 1,
      "5087": 1,
      "5097": 1,
      "5103": 1,
      "5105": 1,
      "5118": 1,
      "5131": 1,
      "5209": 1,
      "5213": 1,
      "5216": 1,
      "5258": 1,
      "5261": 1,
      "5263": 1,
      "5306": 1,
      "5320": 1,
      "5335": 1,
      "5336": 1,
      "5341": 1,
      "5348": 1,
      "5351": 1,
      "5378": 1,
      "5395": 1,
      "5399": 1,
      "5429": 1,
      "5471": 1,
      "5496": 1,
      "5505": 1,
      "5519": 1,
      "5532": 1,
      "5535": 1,
      "5539": 1,
      "5571": 1,
      "5576": 1,
      "5603": 1,
      "5612": 1,
      "5615": 1,
      "5642": 1,
      "5649": 1,
      "5676": 13,
      "5694": 1,
      "5712": 1,
      "5726": 1,
      "5727": 1,
      "5728": 1,
      "5735": 1,
      "5740": 1,
      "5746": 1,
      "5754": 1,
      "5762": 1,
      "5772": 1,
      "5777": 1,
      "5805": 1,
      "5810": 1,
      "5838": 1,
      "5840": 132,
      "5846": 1,
      "5855": 1,
      "5866": 1,
      "5869": 1,
      "5885": 1,
      "5907": 1,
      "5912": 1,
      "5942": 1,
      "5956": 1,
      "5963": 1,
      "6052": 1,
      "6063": 1,
      "6064": 1,
      "6083": 1,
      "6086": 1,
      "6125": 1,
      "6202": 1,
      "6233": 1,
      "6249": 1,
      "6250": 1,
      "6265": 1,
      "6267": 1,
      "6275": 1,
      "6277": 1,
      "6299": 1,
      "6386": 1,
      "6421": 1,
      "6428": 1,
      "6449": 1,
      "6493": 1,
      "6510": 1,
      "6534": 1,
      "6558": 1,
      "6563": 1,
      "6657": 1,
      "6709": 1,
      "6710": 1,
      "6726": 1,
      "6732": 1,
      "6736": 1,
      "6752": 1,
      "6770": 2,
      "6811": 1,
      "6812": 1,
      "6822": 2,
      "6843": 1,
      "6846": 1,
      "6854": 1,
      "6878": 1,
      "6890": 1,
      "6910": 1,
      "6912": 1,
      "6916": 1,
      "6938": 1,
      "6948": 1,
      "6953": 1,
      "6982": 1,
      "6989": 1,
      "6992": 1,
      "7006": 2,
      "7012": 1,
      "7013": 1,
      "7021": 1,
      "7025": 1,
      "7030": 1,
      "7031": 1,
      "7034": 1,
      "7038": 2,
      "7059": 1,
      "7069": 1,
      "7104": 1,
      "7111": 1,
      "7136": 15,
      "7150": 1,
      "7156": 1,
      "7200": 1,
      "7210": 1,
      "7218": 1,
      "7222": 1,
      "7224": 1,
      "7236": 1,
      "7270": 1,
      "7281": 1,
      "7300": 161,
      "7305": 1,
      "7314": 2,
      "7328": 1,
      "7330": 1,
      "7341": 1,
      "7353": 1,
      "7361": 1,
      "7364": 1,
      "7380": 1,
      "7384": 1,
      "7406": 1,
      "7409": 1,
      "7410": 1,
      "7424": 1,
      "7430": 1,
      "7443": 1,
      "7444": 1,
      "7454": 1,
      "7456": 1,
      "7460": 1,
      "7481": 1,
      "7496": 1,
      "7505": 1,
      "7541": 1,
      "7558": 1,
      "7559": 1,
      "7583": 1,
      "7626": 2,
      "7632": 1,
      "7639": 1,
      "7647": 1,
      "7648": 1,
      "7649": 1,
      "7651": 1,
      "7674": 1,
      "7676": 1,
      "7685": 1,
      "7693": 1,
      "7698": 1,
      "7703": 1,
      "7705": 1,
      "7758": 1,
      "7773": 1,
      "7791": 1,
      "7804": 1,
      "7811": 1,
      "7821": 1,
      "7829": 1,
      "7831": 1,
      "7840": 1,
      "7841": 2,
      "7859": 1,
      "7864": 1,
      "7872": 1,
      "7880": 1,
      "7893": 2,
      "7895": 1,
      "7931": 1,
      "7944": 1,
      "7945": 1,
      "7955": 1,
      "7969": 1,
      "7980": 1,
      "8008": 1,
      "8015": 1,
      "8054": 1,
      "8062": 1,
      "8066": 1,
      "8076": 1,
      "8093": 1,
      "8094": 1,
      "8108": 1,
      "8119": 1,
      "8127": 1,
      "8150": 1,
      "8166": 1,
      "8191": 1,
      "8192": 1,
      "8195": 1,
      "8204": 1,
      "8206": 1,
      "8208": 1,
      "8220": 1,
      "8223": 1,
      "8230": 1,
      "8251": 1,
      "8252": 1,
      "8271": 1,
      "8308": 1,
      "8316": 1,
      "8353": 1,
      "8377": 1,
      "8381": 1,
      "8384": 1,
      "8406": 1,
      "8431": 1,
      "8437": 1,
      "8463": 1,
      "8464": 1,
      "8490": 1,
      "8499": 1,
      "8509": 1,
      "8514": 1,
      "8520": 1,
      "8529": 1,
      "8530": 1,
      "8531": 1,
      "8560": 1,
      "8580": 1,
      "8590": 1,
      "8596": 15,
      "8608": 1,
      "8612": 1,
      "8633": 1,
      "8655": 1,
      "8671": 1,
      "8676": 1,
      "8679": 1,
      "8690": 1,
      "8697": 2,
      "8705": 1,
      "8723": 1,
      "8732": 2,
      "8740": 1,
      "8746": 1,
      "8760": 232,
      "8776": 1,
      "8819": 1,
      "8830": 1,
      "8832": 1,
      "8837": 1,
      "8846": 1,
      "8848": 1,
      "8850": 1,
      "8856": 1,
      "8858": 1,
      "8894": 1,
      "8895": 1,
      "8900": 1,
      "8905": 1,
      "8910": 1,
      "8916": 1,
      "8923": 1,
      "8948": 1,
      "8950": 1,
      "8954": 1,
      "8959": 1,
      "8961": 1,
      "8969": 1,
      "8977": 1,
      "8980": 1,
      "8981": 1,
      "8983": 1,
      "8993": 1,
      "9005": 1,
      "9007": 1,
      "9013": 1,
      "9029": 1,
      "9035": 1,
      "9097": 1,
      "9110": 1,
      "9138": 1,
      "9147": 1,
      "9156": 1,
      "9173": 2,
      "9191": 1,
      "9249": 1,
      "9265": 1,
      "9270": 1,
      "9271": 1,
      "9300": 1,
      "9315": 1,
      "9332": 1,
      "9335": 1,
      "9358": 1,
      "9364": 1,
      "9399": 1,
      "9411": 2,
      "9412": 1,
      "9431": 1,
      "9436": 1,
      "9442": 1,
      "9457": 1,
      "9469": 1,
      "9484": 1,
      "9485": 1,
      "9491": 1,
      "9492": 1,
      "9501": 1,
      "9526": 2,
      "9536": 1,
      "9553": 1,
      "9587": 1,
      "9601": 1,
      "9605": 1,
      "9608": 1,
      "9625": 1,
      "9636": 1,
      "9648": 1,
      "9652": 1,
      "9658": 1,
      "9659": 1,
      "9673": 1,
      "9676": 1,
      "9688": 1,
      "9690": 1,
      "9703": 1,
      "9710": 1,
      "9712": 1,
      "9723": 1,
      "9744": 1,
      "9752": 1,
      "9754": 1,
      "9758": 1,
      "9797": 1,
      "9803": 1,
      "9804": 1,
      "9805": 1,
      "9831": 1,
      "9850": 1,
      "9867": 1,
      "9900": 1,
      "9910": 1,
      "9917": 1,
      "9918": 1,
      "9929": 1,
      "9932": 1,
      "9947": 1,
      "9950": 1,
      "9952": 1,
      "9976": 1,
      "9989": 1,
      "10002": 1,
      "10004": 1,
      "10008": 2,
      "10016": 1,
      "10017": 1,
      "10026": 1,
      "10027": 1,
      "10028": 1,
      "10034": 1,
      "10047": 1,
      "10049": 1,
      "10052": 1,
      "10056": 20,
      "10057": 1,
      "10061": 1,
      "10077": 1,
      "10087": 1,
      "10090": 1,
      "10106": 1,
      "10150": 1,
      "10157": 1,
      "10175": 1,
      "10220": 261,
      "10229": 1,
      "10248": 1,
      "10250": 1,
      "10278": 1,
      "10279": 2,
      "10287": 1,
      "10289": 1,
      "10298": 1,
      "10300": 1,
      "10301": 1,
      "10326": 1,
      "10340": 1,
      "10345": 1,
      "10354": 1,
      "10379": 1,
      "10381": 1,
      "10396": 2,
      "10401": 1,
      "10414": 1,
      "10415": 1,
      "10437": 1,
      "10439": 1,
      "10484": 2,
      "10493": 1,
      "10497": 1,
      "10499": 1,
      "10526": 1,
      "10534": 1,
      "10539": 1,
      "10547": 1,
      "10590": 1,
      "10615": 1,
      "10618": 1,
      "10626": 1,
      "10681": 1,
      "10685": 1,
      "10687": 1,
      "10696": 1,
      "10726": 1,
      "10728": 1,
      "10732": 1,
      "10760": 1,
      "10779": 1,
      "10783": 2,
      "10789": 1,
      "10798": 1,
      "10803": 1,
      "10808": 1,
      "10815": 1,
      "10853": 1,
      "10857": 1,
      "10867": 1,
      "10872": 1,
      "10882": 1,
      "10883": 1,
      "10884": 1,
      "10888": 1,
      "10912": 1,
      "10913": 1,
      "10918": 2,
      "10921": 1,
      "10923": 1,
      "10924": 1,
      "10977": 1,
      "10993": 1,
      "11017": 1,
      "11018": 1,
      "11036": 1,
      "11048": 1,
      "11085": 1,
      "11108": 1,
      "11112": 2,
      "11118": 2,
      "11124": 1,
      "11128": 1,
      "11133": 2,
      "11135": 1,
      "11144": 1,
      "11171": 1,
      "11184": 1,
      "11194": 1,
      "11227": 1,
      "11235": 1,
      "11248": 1,
      "11252": 1,
      "11265": 1,
      "11266": 1,
      "11270": 1,
      "11307": 1,
      "11333": 1,
      "11344": 1,
      "11353": 1,
      "11366": 1,
      "11378": 1,
      "11380": 1,
      "11382": 1,
      "11386": 1,
      "11396": 1,
      "11405": 1,
      "11407": 1,
      "11435": 1,
      "11436": 7,
      "11441": 1,
      "11457": 1,
      "11459": 1,
      "11461": 1,
      "11466": 2,
      "11473": 1,
      "11491": 1,
      "11498": 2,
      "11516": 35,
      "11517": 1,
      "11532": 1,
      "11543": 1,
      "11560": 1,
      "11566": 1,
      "11580": 1,
      "11586": 1,
      "11590": 1,
      "11592": 1,
      "11606": 1,
      "11658": 1,
      "11665": 1,
      "11680": 310,
      "11700": 1,
      "11709": 1,
      "11751": 1,
      "11760": 1,
      "11769": 1,
      "11779": 1,
      "11795": 1,
      "11804": 1,
      "11810": 1,
      "11820": 1,
      "11824": 2,
      "11862": 1,
      "11868": 1,
      "11882": 1,
      "11907": 1,
      "11910": 1,
      "11919": 1,
      "11932": 1,
      "11947": 1,
      "11958": 1,
      "11961": 1,
      "11968": 1,
      "11989": 1,
      "11998": 1,
      "12008": 1,
      "12015": 1,
      "12019": 1,
      "12022": 1,
      "12028": 1,
      "12030": 1,
      "12043": 1,
      "12046": 1,
      "12049": 1,
      "12056": 1,
      "12068": 1,
      "12077": 1,
      "12096": 1,
      "12104": 1,
      "12120": 1,
      "12127": 1,
      "12128": 1,
      "12132": 1,
      "12133": 1,
      "12148": 1,
      "12169": 1,
      "12179": 1,
      "12218": 1,
      "12243": 1,
      "12256": 1,
      "12269": 1,
      "12270": 1,
      "12274": 1,
      "12277": 1,
      "12279": 1,
      "12283": 1,
      "12303": 1,
      "12309": 1,
      "12310": 1,
      "12323": 1,
      "12326": 1,
      "12345": 1,
      "12371": 1,
      "12383": 1,
      "12394": 1,
      "12395": 1,
      "12412": 1,
      "12424": 1,
      "12445": 2,
      "12461": 1,
      "12462": 1,
      "12466": 1,
      "12468": 1,
      "12477": 1,
      "12497": 1,
      "12500": 1,
      "12528": 1,
      "12535": 1,
      "12545": 1,
      "12563": 1,
      "12576": 1,
      "12583": 1,
      "12598": 1,
      "12612": 1,
      "12623": 1,
      "12640": 1,
      "12641": 1,
      "12653": 1,
      "12658": 1,
      "12668": 1,
      "12670": 1,
      "12682": 1,
      "12707": 1,
      "12711": 2,
      "12716": 1,
      "12746": 1,
      "12753": 2,
      "12756": 1,
      "12795": 1,
      "12799": 1,
      "12809": 1,
      "12814": 1,
      "12829": 1,
      "12836": 1,
      "12843": 1,
      "12844": 2,
      "12869": 1,
      "12880": 1,
      "12890": 1,
      "12892": 1,
      "12896": 5,
      "12902": 1,
      "12914": 1,
      "12933": 1,
      "12950": 1,
      "12964": 1,
      "12976": 25,
      "12994": 2,
      "13005": 1,
      "13027": 1,
      "13041": 1,
      "13052": 1,
      "13066": 1,
      "13121": 1,
      "13124": 1,
      "13127": 1,
      "13129": 1,
      "13140": 325,
      "13141": 1,
      "13158": 1,
      "13168": 1,
      "13176": 1,
      "13181": 1,
      "13186": 2,
      "13193": 1,
      "13204": 1,
      "13246": 1,
      "13256": 1,
      "13281": 1,
      "13300": 1,
      "13309": 1,
      "13326": 1,
      "13354": 1,
      "13380": 1,
      "13393": 1,
      "13431": 1,
      "13465": 1,
      "13481": 1,
      "13488": 1,
      "13491": 1,
      "13530": 1,
      "13545": 1,
      "13608": 1,
      "13621": 1,
      "13637": 1,
      "13647": 1,
      "13674": 1,
      "13683": 1,
      "13684": 1,
      "13697": 1,
      "13724": 1,
      "13732": 2,
      "13742": 1,
      "13761": 1,
      "13777": 1,
      "13841": 1,
      "13866": 1,
      "13873": 1,
      "13904": 1,
      "13935": 1,
      "13939": 1,
      "13948": 1,
      "13973": 1,
      "13990": 1,
      "13992": 1,
      "13996": 1,
      "14031": 1,
      "14032": 1,
      "14086": 1,
      "14095": 1,
      "14096": 2,
      "14109": 1,
      "14110": 1,
      "14118": 1,
      "14126": 1,
      "14133": 1,
      "14135": 1,
      "14156": 1,
      "14169": 1,
      "14178": 1,
      "14237": 1,
      "14252": 1,
      "14267": 1,
      "14275": 1,
      "14292": 1,
      "14298": 1,
      "14311": 1,
      "14312": 1,
      "14319": 1,
      "14337": 1,
      "14347": 1,
      "14354": 1,
      "14356": 16,
      "14360": 1,
      "14361": 1,
      "14372": 1,
      "14382": 1,
      "14388": 1,
      "14391": 1,
      "14396": 1,
      "14400": 1,
      "14433": 1,
      "14436": 45,
      "14446": 1,
      "14473": 1,
      "14484": 1,
      "14563": 1,
      "14570": 1,
      "14589": 1,
      "14594": 1,
      "14599": 1,
      "14600": 290,
      "14605": 1,
      "14632": 1,
      "14645": 1,
      "14657": 1,
      "14675": 1,
      "14687": 1,
      "14703": 1,
      "14707": 1,
      "14720": 1,
      "14730": 2,
      "14734": 1,
      "14738": 1,
      "14744": 1,
      "14759": 1,
      "14771": 1,
      "14785": 1,
      "14819": 1,
      "14850": 1,
      "14859": 1,
      "14884": 1,
      "14902": 1,
      "14905": 1,
      "14926": 1,
      "14935": 1,
      "14945": 1,
      "14955": 1,
      "14966": 1,
      "14968": 1,
      "14969": 1,
      "14983": 1,
      "15004": 2,
      "15021": 1,
      "15031": 1,
      "15036": 1,
      "15037": 1,
      "15042": 1,
      "15049": 1,
      "15060": 1,
      "15064": 1,
      "15070": 2,
      "15076": 1,
      "15086": 1,
      "15110": 1,
      "15130": 1,
      "15172": 1,
      "15175": 1,
      "15214": 1,
      "15216": 1,
      "15230": 1,
      "15239": 1,
      "15240": 1,
      "15259": 1,
      "15264": 1,
      "15284": 1,
      "15300": 1,
      "15312": 1,
      "15319": 1,
      "15336": 1,
      "15352": 1,
      "15356": 1,
      "15363": 1,
      "15389": 1,
      "15392": 1,
      "15399": 1,
      "15415": 1,
      "15423": 1,
      "15456": 1,
      "15471": 1,
      "15472": 1,
      "15476": 1,
      "15492": 2,
      "15501": 1,
      "15509": 1,
      "15518": 1,
      "15564": 1,
      "15570": 1,
      "15575": 1,
      "15606": 1,
      "15611": 1,
      "15618": 1,
      "15622": 1,
      "15626": 1,
      "15631": 1,
      "15632": 1,
      "15648": 1,
      "15681": 1,
      "15687": 1,
      "15697": 1,
      "15723": 1,
      "15730": 1,
      "15755": 1,
      "15761": 1,
      "15764": 5,
      "15771": 1,
      "15775": 1,
      "15778": 1,
      "15802": 1,
      "15816": 12,
      "15836": 1,
      "15843": 1,
      "15866": 1,
      "15891": 2,
      "15892": 1,
      "15896": 46,
      "15951": 1,
      "15959": 2,
      "15983": 1,
      "15985": 1,
      "15986": 1,
      "15996": 1,
      "16024": 1,
      "16047": 1,
      "16055": 1,
      "16060": 273,
      "16061": 1,
      "16065": 1,
      "16075": 1,
      "16078": 1,
      "16088": 1,
      "16090": 2,
      "16092": 1,
      "16093": 1,
      "16096": 1,
      "16110": 1,
      "16115": 1,
      "16117": 1,
      "16134": 1,
      "16135": 1,
      "16175": 1,
      "16180": 1,
      "16195": 1,
      "16204": 1,
      "16217": 1,
      "16222": 1,
      "16223": 1,
      "16226": 1,
      "16257": 1,
      "16268": 1,
      "16272": 1,
      "16310": 1,
      "16320": 1,
      "16326": 1,
      "16352": 1,
      "16355": 1,
      "16360": 1,
      "16366": 2,
      "16382": 1,
      "16386": 1,
      "16390": 1,
      "16404": 1,
      "16415": 1,
      "16417": 1,
      "16426": 1,
      "16433": 1,
      "16440": 1,
      "16448": 1,
      "16456": 1,
      "16460": 1,
      "16461": 1,
      "16473": 1,
      "16474": 1,
      "16478": 1,
      "16487": 1,
      "16508": 1,
      "16510": 1,
      "16513": 1,
      "16518": 1,
      "16531": 1,
      "16546": 1,
      "16568": 1,
      "16580": 1,
      "16592": 1,
      "16610": 1,
      "16631": 1,
      "16653": 1,
      "16672": 1,
      "16679": 1,
      "16723": 1,
      "16738": 1,
      "16763": 1,
      "16768": 1,
      "16786": 1,
      "16799": 1,
      "16844": 1,
      "16867": 1,
      "16874": 1,
      "16877": 1,
      "16885": 1,
      "16892": 1,
      "16910": 1,
      "16940": 1,
      "16949": 1,
      "16951": 1,
      "16952": 1,
      "16968": 1,
      "16980": 1,
      "16994": 1,
      "16999": 1,
      "17011": 1,
      "17031": 1,
      "17032": 1,
      "17034": 1,
      "17039": 1,
      "17040": 1,
      "17059": 1,
      "17096": 1,
      "17103": 1,
      "17106": 1,
      "17130": 1,
      "17136": 1,
      "17149": 1,
      "17159": 1,
      "17167": 1,
      "17209": 1,
      "17216": 1,
      "17224": 2,
      "17234": 1,
      "17264": 1,
      "17276": 17,
      "17283": 1,
      "17288": 1,
      "17292": 1,
      "17301": 1,
      "17315": 1,
      "17353": 1,
      "17356": 46,
      "17359": 1,
      "17384": 1,
      "17389": 1,
      "17419": 1,
      "17436": 1,
      "17444": 1,
      "17446": 1,
      "17448": 1,
      "17458": 1,
      "17461": 1,
      "17471": 1,
      "17483": 1,
      "17498": 1,
      "17507": 1,
      "17510": 1,
      "17520": 301,
      "17548": 1,
      "17554": 1,
      "17560": 1,
      "17561": 1,
      "17563": 1,
      "17568": 1,
      "17573": 1,
      "17580": 1,
      "17621": 1,
      "17639": 1,
      "17652": 2,
      "17656": 1,
      "17681": 1,
      "17683": 1,
      "17685": 1,
      "17705": 1,
      "17748": 1,
      "17756": 1,
      "17766": 1,
      "17767": 1,
      "17775": 1,
      "17789": 1,
      "17791": 1,
      "17796": 1,
      "17804": 1,
      "17833": 1,
      "17848": 1,
      "17858": 1,
      "17860": 1,
      "17861": 1,
      "17863": 1,
      "17869": 1,
      "17901": 2,
      "17903": 1,
      "17918": 1,
      "17960": 1,
      "17966": 1,
      "17968": 1,
      "17983": 1,
      "17989": 1,
      "18000": 1,
      "18020": 1,
      "18022": 1,
      "18041": 1,
      "18042": 1,
      "18059": 1,
      "18091": 1,
      "18095": 1,
      "18096": 1,
      "18117": 1,
      "18184": 1,
      "18186": 1,
      "18188": 1,
      "18197": 1,
      "18232": 1,
      "18233": 1,
      "18240": 1,
      "18247": 1,
      "18273": 1,
      "18275": 1,
      "18310": 1,
      "18325": 1,
      "18330": 1,
      "18348": 1,
      "18349": 1,
      "18356": 1,
      "18373": 2,
      "18407": 1,
      "18488": 1,
      "18500": 1,
      "18503": 1,
      "18515": 1,
      "18517": 1,
      "18551": 1,
      "18557": 1,
      "18562": 1,
      "18563": 1,
      "18576": 1,
      "18594": 1,
      "18638": 1,
      "18645": 1,
      "18656": 1,
      "18660": 1,
      "18663": 1,
      "18664": 1,
      "18671": 1,
      "18676": 1,
      "18677": 1,
      "18684": 4,
      "18686": 1,
      "18709": 1,
      "18736": 19,
      "18739": 1,
      "18758": 1,
      "18770": 1,
      "18802": 1,
      "18816": 45,
      "18824": 1,
      "18830": 1,
      "18847": 1,
      "18849": 1,
      "18865": 1,
      "18877": 1,
      "18879": 1,
      "18898": 1,
      "18930": 1,
      "18980": 270,
      "19035": 1,
      "19045": 1,
      "19051": 1,
      "19060": 2,
      "19104": 1,
      "19110": 1,
      "19113": 1,
      "19121": 1,
      "19132": 1,
      "19148": 1,
      "19169": 1,
      "19177": 1,
      "19180": 1,
      "19199": 1,
      "19206": 1,
      "19220": 1,
      "19223": 1,
      "19250": 2,
      "19254": 1,
      "19279": 1,
      "19295": 1,
      "19298": 1,
      "19341": 1,
      "19346": 1,
      "19355": 1,
      "19358": 1,
      "19362": 1,
      "19367": 1,
      "19368": 1,
      "19380": 1,
      "19390": 1,
      "19405": 1,
      "19407": 1,
      "19423": 1,
      "19426": 1,
      "19442": 1,
      "19443": 1,
      "19444": 1,
      "19448": 1,
      "19463": 1,
      "19468": 1,
      "19495": 1,
      "19510": 1,
      "19531": 1,
      "19570": 1,
      "19583": 1,
      "19607": 1,
      "19630": 1,
      "19702": 1,
      "19744": 1,
      "19747": 1,
      "19773": 1,
      "19776": 1,
      "19781": 1,
      "19838": 1,
      "19849": 1,
      "19850": 1,
      "19868": 1,
      "19881": 1,
      "19928": 1,
      "19976": 1,
      "20017": 1,
      "20052": 1,
      "20057": 1,
      "20066": 1,
      "20069": 1,
      "20108": 1,
      "20136": 1,
      "20142": 2,
      "20146": 1,
      "20164": 2,
      "20165": 1,
      "20190": 1,
      "20191": 1,
      "20196": 22,
      "20217": 1,
      "20223": 1,
      "20233": 1,
      "20243": 2,
      "20248": 1,
      "20259": 1,
      "20262": 1,
      "20276": 41,
      "20297": 1,
      "20298": 1,
      "20303": 1,
      "20304": 2,
      "20329": 1,
      "20338": 1,
      "20350": 1,
      "20392": 1,
      "20400": 1,
      "20403": 1,
      "20406": 1,
      "20419": 1,
      "20440": 244,
      "20456": 1,
      "20459": 1,
      "20480": 1,
      "20486": 1,
      "20520": 2,
      "20523": 1,
      "20549": 1,
      "20565": 1,
      "20566": 1,
      "20589": 1,
      "20594": 1,
      "20631": 1,
      "20642": 1,
      "20647": 1,
      "20655": 1,
      "20659": 1,
      "20660": 2,
      "20662": 1,
      "20727": 1,
      "20737": 1,
      "20749": 1,
      "20751": 1,
      "20757": 1,
      "20760": 1,
      "20772": 1,
      "20776": 1,
      "20796": 1,
      "20802": 1,
      "20809": 1,
      "20824": 1,
      "20852": 1,
      "20868": 1,
      "20871": 1,
      "20886": 1,
      "20903": 1,
      "20951": 1,
      "20973": 1,
      "21005": 2,
      "21013": 1,
      "21018": 1,
      "21024": 1,
      "21029": 1,
      "21036": 1,
      "21056": 1,
      "21089": 1,
      "21098": 1,
      "21107": 1,
      "21123": 1,
      "21127": 1,
      "21147": 1,
      "21151": 1,
      "21164": 1,
      "21171": 1,
      "21188": 1,
      "21198": 1,
      "21247": 1,
      "21283": 1,
      "21287": 1,
      "21300": 1,
      "21363": 1,
      "21367": 1,
      "21393": 1,
      "21412": 1,
      "21420": 1,
      "21429": 1,
      "21465": 1,
      "21473": 1,
      "21486": 1,
      "21577": 1,
      "21604": 1,
      "21619": 1,
      "21626": 1,
      "21638": 1,
      "21639": 1,
      "21656": 22,
      "21662": 1,
      "21713": 1,
      "21717": 1,
      "21729": 1,
      "21735": 1,
      "21736": 42,
      "21738": 1,
      "21746": 1,
      "21773": 1,
      "21803": 1,
      "21810": 1,
      "21812": 1,
      "21837": 1,
      "21839": 2,
      "21845": 1,
      "21847": 1,
      "21867": 1,
      "21882": 1,
      "21900": 227,
      "21907": 2,
      "21921": 1,
      "21974": 1,
      "21980": 3,
      "21991": 1,
      "22002": 1,
      "22030": 1,
      "22057": 1,
      "22059": 1,
      "22114": 1,
      "22115": 1,
      "22120": 1,
      "22152": 1,
      "22156": 1,
      "22165": 1,
      "22166": 1,
      "22182": 1,
      "22184": 1,
      "22222": 1,
      "22233": 1,
      "22288": 1,
      "22307": 1,
      "22318": 1,
      "22324": 1,
      "22338": 1,
      "22353": 1,
      "22363": 1,
      "22367": 1,
      "22387": 1,
      "22397": 1,
      "22400": 1,
      "22402": 1,
      "22403": 1,
      "22484": 1,
      "22514": 1,
      "22575": 1,
      "22600": 1,
      "22624": 1,
      "22635": 1,
      "22693": 1,
      "22728": 1,
      "22738": 1,
      "22742": 1,
      "22743": 1,
      "22769": 1,
      "22803": 1,
      "22812": 1,
      "22813": 1,
      "22874": 1,
      "22879": 1,
      "22891": 1,
      "22897": 1,
      "22904": 1,
      "22923": 1,
      "22984": 1,
      "23052": 1,
      "23064": 2,
      "23074": 1,
      "23076": 1,
      "23114": 1,
      "23116": 24,
      "23135": 1,
      "23148": 1,
      "23153": 1,
      "23155": 1,
      "23168": 1,
      "23170": 1,
      "23196": 45,
      "23197": 1,
      "23239": 1,
      "23276": 1,
      "23297": 1,
      "23320": 1,
      "23329": 1,
      "23339": 1,
      "23360": 173,
      "23376": 1,
      "23388": 1,
      "23390": 1,
      "23414": 1,
      "23415": 1,
      "23440": 3,
      "23458": 1,
      "23481": 1,
      "23494": 1,
      "23507": 2,
      "23652": 1,
      "23657": 1,
      "23674": 1,
      "23732": 1,
      "23743": 1,
      "23761": 1,
      "23829": 1,
      "23839": 1,
      "23912": 1,
      "23914": 1,
      "23915": 1,
      "23932": 1,
      "23933": 1,
      "23944": 1,
      "23947": 1,
      "23978": 1,
      "23995": 1,
      "23998": 1,
      "24045": 1,
      "24078": 1,
      "24081": 1,
      "24101": 1,
      "24107": 1,
      "24113": 1,
      "24136": 1,
      "24144": 1,
      "24151": 1,
      "24179": 1,
      "24180": 1,
      "24189": 1,
      "24235": 1,
      "24252": 1,
      "24278": 1,
      "24284": 1,
      "24332": 1,
      "24361": 1,
      "24364": 1,
      "24372": 1,
      "24386": 1,
      "24392": 1,
      "24405": 1,
      "24416": 1,
      "24449": 1,
      "24456": 1,
      "24462": 1,
      "24480": 1,
      "24483": 1,
      "24524": 4,
      "24552": 1,
      "24566": 1,
      "24576": 25,
      "24615": 1,
      "24621": 1,
      "24626": 1,
      "24655": 1,
      "24656": 36,
      "24662": 1,
      "24734": 1,
      "24740": 1,
      "24758": 1,
      "24804": 1,
      "24812": 1,
      "24820": 160,
      "24828": 1,
      "24834": 1,
      "24845": 2,
      "24906": 1,
      "24973": 1,
      "24977": 1,
      "24989": 1,
      "24997": 1,
      "25047": 1,
      "25110": 1,
      "25118": 1,
      "25123": 1,
      "25132": 1,
      "25136": 1,
      "25145": 1,
      "25180": 1,
      "25193": 1,
      "25232": 1,
      "25235": 1,
      "25247": 1,
      "25252": 1,
      "25257": 1,
      "25284": 1,
      "25355": 1,
      "25372": 1,
      "25412": 1,
      "25423": 1,
      "25446": 1,
      "25461": 1,
      "25475": 1,
      "25486": 1,
      "25513": 1,
      "25533": 1,
      "25541": 1,
      "25561": 1,
      "25580": 1,
      "25605": 1,
      "25609": 1,
      "25669": 1,
      "25675": 1,
      "25698": 1,
      "25712": 1,
      "25724": 1,
      "25777": 1,
      "25797": 1,
      "25799": 1,
      "25826": 1,
      "25833": 1,
      "25887": 1,
      "25924": 1,
      "25931": 1,
      "25934": 2,
      "25937": 1,
      "25941": 1,
      "25972": 1,
      "25976": 1,
      "25984": 3,
      "26001": 1,
      "26036": 17,
      "26037": 1,
      "26045": 1,
      "26069": 1,
      "26092": 1,
      "26116": 21,
      "26129": 1,
      "26135": 1,
      "26146": 1,
      "26197": 1,
      "26239": 1,
      "26247": 1,
      "26249": 1,
      "26265": 1,
      "26280": 94,
      "26291": 1,
      "26294": 1,
      "26296": 1,
      "26303": 1,
      "26305": 1,
      "26348": 1,
      "26360": 2,
      "26432": 1,
      "26471": 1,
      "26499": 1,
      "26604": 1,
      "26625": 1,
      "26627": 1,
      "26630": 1,
      "26677": 1,
      "26693": 1,
      "26711": 1,
      "26761": 1,
      "26866": 1,
      "26891": 1,
      "26894": 1,
      "26919": 1,
      "26924": 1,
      "26943": 1,
      "27028": 1,
      "27055": 1,
      "27065": 1,
      "27114": 1,
      "27170": 1,
      "27177": 1,
      "27188": 1,
      "27213": 1,
      "27241": 1,
      "27311": 1,
      "27323": 1,
      "27337": 1,
      "27355": 1,
      "27359": 1,
      "27374": 1,
      "27406": 1,
      "27413": 1,
      "27414": 1,
      "27484": 1,
      "27496": 10,
      "27499": 1,
      "27576": 17,
      "27589": 1,
      "27667": 1,
      "27671": 1,
      "27679": 1,
      "27686": 1,
      "27687": 1,
      "27700": 1,
      "27732": 1,
      "27740": 91,
      "27787": 1,
      "27815": 1,
      "27816": 1,
      "27820": 1,
      "27857": 1,
      "27864": 1,
      "27884": 1,
      "27931": 1,
      "27990": 1,
      "28014": 1,
      "28019": 1,
      "28021": 1,
      "28075": 1,
      "28124": 1,
      "28128": 1,
      "28167": 1,
      "28170": 1,
      "28219": 1,
      "28312": 1,
      "28343": 1,
      "28381": 1,
      "28434": 1,
      "28460": 1,
      "28515": 1,
      "28549": 1,
      "28617": 1,
      "28726": 1,
      "28763": 1,
      "28850": 1,
      "28892": 1,
      "28895": 1,
      "28904": 3,
      "28930": 1,
      "28956": 9,
      "28977": 1,
      "29012": 1,
      "29022": 1,
      "29036": 16,
      "29097": 1,
      "29120": 1,
      "29122": 1,
      "29177": 1,
      "29200": 67,
      "29247": 1,
      "29264": 1,
      "29266": 1,
      "29280": 3,
      "29388": 1,
      "29424": 1,
      "29462": 1,
      "29468": 1,
      "29726": 1,
      "29818": 1,
      "29950": 1,
      "30002": 1,
      "30095": 1,
      "30141": 1,
      "30215": 1,
      "30221": 1,
      "30279": 1,
      "30364": 2,
      "30370": 1,
      "30407": 1,
      "30416": 8,
      "30487": 1,
      "30496": 14,
      "30522": 1,
      "30569": 1,
      "30573": 1,
      "30593": 1,
      "30660": 43,
      "30740": 1,
      "30744": 1,
      "30831": 1,
      "30900": 1,
      "30918": 1,
      "30946": 1,
      "31001": 1,
      "31065": 1,
      "31204": 1,
      "31304": 1,
      "31306": 1,
      "31327": 1,
      "31446": 1,
      "31483": 1,
      "31509": 1,
      "31534": 1,
      "31536": 1,
      "31546": 1,
      "31601": 1,
      "31636": 1,
      "31771": 1,
      "31797": 1,
      "31824": 1,
      "31876": 6,
      "31956": 12,
      "32019": 1,
      "32068": 1,
      "32120": 26,
      "32200": 1,
      "32272": 1,
      "32332": 1,
      "32533": 1,
      "32618": 1,
      "32697": 1,
      "32742": 1,
      "32779": 1,
      "32805": 1,
      "32810": 1,
      "32905": 1,
      "32922": 1,
      "32951": 1,
      "32991": 1,
      "33000": 1,
      "33032": 1,
      "33059": 1,
      "33221": 1,
      "33336": 5,
      "33416": 8,
      "33480": 1,
      "33578": 1,
      "33580": 26,
      "33584": 1,
      "33611": 1,
      "33623": 1,
      "33691": 1,
      "33695": 1,
      "33711": 1,
      "33720": 1,
      "34326": 1,
      "34426": 1,
      "34439": 1,
      "34441": 1,
      "34742": 1,
      "34744": 1,
      "34804": 1,
      "34846": 1,
      "34876": 5,
      "35040": 13,
      "35120": 1,
      "35127": 1,
      "35165": 1,
      "35210": 1,
      "35313": 1,
      "35437": 1,
      "35542": 1,
      "35664": 1,
      "35673": 1,
      "35733": 1,
      "35764": 1,
      "35773": 1,
      "35815": 1,
      "35862": 1,
      "35877": 1,
      "35987": 1,
      "36149": 1,
      "36214": 1,
      "36242": 1,
      "36283": 1,
      "36307": 1,
      "36336": 2,
      "36338": 1,
      "36366": 1,
      "36467": 1,
      "36500": 6,
      "36580": 1,
      "36609": 1,
      "36731": 1,
      "36830": 1,
      "37477": 1,
      "37664": 1,
      "37716": 2,
      "37734": 1,
      "37766": 1,
      "37796": 4,
      "37932": 1,
      "37960": 9,
      "37995": 1,
      "38037": 1,
      "38095": 1,
      "38247": 1,
      "38480": 1,
      "38893": 1,
      "38908": 1,
      "38935": 1,
      "39093": 1,
      "39121": 1,
      "39256": 2,
      "39420": 1,
      "39436": 1,
      "39576": 1,
      "39667": 1,
      "39702": 1,
      "39801": 1,
      "39846": 1,
      "40070": 1,
      "40076": 1,
      "40167": 1,
      "40633": 1,
      "40803": 1,
      "40880": 3,
      "41007": 1,
      "41504": 1,
      "41676": 1,
      "42340": 4,
      "42486": 1,
      "43381": 1,
      "43514": 1,
      "43938": 1,
      "45260": 1,
      "46469": 1,
      "46490": 1,
      "46556": 2,
      "48180": 2,
      "49589": 1,
      "50148": 1,
      "50930": 1,
      "54153": 1,
      "65536": 5
   },
   "started": "2020-05-07T13:53:26.891Z",
   "trafficStats": {
      "incomingCompressionRatio": 0.8504757537841797,
      "incomingOctetsAppLevel": 131072000,
      "incomingOctetsWebSocketLevel": 111473558,
      "incomingOctetsWireLevel": 111483558,
      "incomingWebSocketFrames": 1000,
      "incomingWebSocketMessages": 1000,
      "incomingWebSocketOverhead": 8.970737257709133e-05,
      "outgoingCompressionRatio": 0.8529337692260742,
      "outgoingOctetsAppLevel": 131072000,
      "outgoingOctetsWebSocketLevel": 111795735,
      "outgoingOctetsWireLevel": 111809735,
      "outgoingWebSocketFrames": 1000,
      "outgoingWebSocketMessages": 1000,
      "outgoingWebSocketOverhead": 0.0001252283908683994,
      "preopenIncomingOctetsWireLevel": 245,
      "preopenOutgoingOctetsWireLevel": 350
   },
   "txFrameStats": {
      "2": 1000,
      "8": 1
   },
   "txOctetStats": {
      "8": 1,
      "350": 1,
      "108368": 1,
      "108388": 1,
      "108394": 1,
      "108401": 1,
      "108410": 1,
      "108419": 1,
      "108420": 1,
      "108425": 1,
      "108433": 1,
      "108438": 1,
      "108444": 1,
      "108449": 1,
      "108463": 1,
      "108464": 2,
      "108469": 1,
      "108474": 1,
      "108492": 1,
      "108496": 2,
      "108497": 1,
      "108499": 1,
      "108501": 1,
      "108510": 1,
      "108512": 1,
      "108513": 1,
      "108517": 1,
      "108524": 1,
      "108541": 2,
      "108546": 1,
      "108549": 2,
      "108551": 1,
      "108552": 1,
      "108558": 1,
      "108559": 2,
      "108560": 1,
      "108564": 1,
      "108568": 2,
      "108570": 1,
      "108571": 1,
      "108575": 1,
      "108577": 1,
      "108579": 1,
      "108580": 1,
      "108582": 1,
      "108591": 1,
      "108594": 1,
      "108601": 2,
      "108603": 1,
      "108615": 1,
      "108616": 3,
      "108622": 1,
      "108624": 2,
      "108625": 1,
      "108632": 1,
      "108634": 1,
      "108635": 1,
      "108638": 1,
      "108644": 1,
      "108650": 1,
      "108652": 2,
      "108653": 1,
      "108655": 1,
      "108656": 1,
      "108661": 1,
      "108665": 2,
      "108666": 1,
      "108667": 1,
      "108670": 1,
      "108675": 2,
      "108676": 1,
      "108678": 1,
      "108679": 1,
      "108693": 1,
      "108695": 1,
      "108701": 1,
      "108707": 1,
      "108710": 1,
      "108711": 1,
      "108712": 2,
      "108716": 1,
      "108719": 2,
      "108722": 1,
      "108724": 1,
      "108727": 1,
      "108729": 2,
      "108731": 1,
      "108735": 2,
      "108737": 1,
      "108739": 1,
      "108740": 1,
      "108743": 2,
      "108746": 1,
      "108747": 1,
      "108748": 1,
      "108750": 1,
      "108753": 3,
      "108755": 3,
      "108759": 1,
      "108760": 1,
      "108761": 1,
      "108762": 2,
      "108763": 1,
      "108764": 1,
      "108765": 2,
      "108766": 1,
      "108767": 3,
      "108768": 2,
      "108770": 2,
      "108773": 1,
      "108774": 2,
      "108777": 1,
      "108778": 1,
      "108781": 1,
      "108782": 1,
      "108783": 1,
      "108784": 2,
      "108786": 1,
      "108797": 1,
      "108798": 1,
      "108802": 1,
      "108804": 1,
      "108807": 1,
      "108809": 1,
      "108812": 1,
      "108818": 1,
      "108821": 2,
      "108824": 1,
      "108825": 1,
      "108826": 1,
      "108830": 1,
      "108831": 1,
      "108833": 1,
      "108837": 1,
      "108838": 1,
      "108841": 1,
      "108842": 1,
      "108851": 1,
      "108860": 1,
      "108862": 1,
      "108869": 1,
      "108891": 1,
      "108900": 1,
      "108902": 1,
      "108925": 1,
      "108931": 1,
      "108934": 1,
      "108941": 1,
      "108949": 1,
      "108950": 1,
      "108964": 1,
      "108965": 1,
      "108970": 1,
      "108977": 1,
      "108979": 1,
      "108982": 1,
      "108988": 1,
      "108992": 1,
      "109002": 1,
      "109004": 1,
      "109007": 1,
      "109017": 1,
      "109030": 1,
      "109046": 1,
      "109050": 2,
      "109058": 1,
      "109063": 1,
      "109074": 1,
      "109077": 1,
      "109078": 1,
      "109086": 1,
      "109087": 1,
      "109090": 1,
      "109092": 1,
      "109103": 1,
      "109105": 1,
      "109112": 1,
      "109117": 1,
      "109119": 1,
      "109121": 1,
      "109128": 1,
      "109131": 1,
      "109134": 1,
      "109140": 1,
      "109141": 1,
      "109152": 1,
      "109161": 1,
      "109163": 1,
      "109164": 1,
      "109171": 1,
      "109176": 1,
      "109178": 1,
      "109182": 1,
      "109184": 1,
      "109199": 2,
      "109204": 1,
      "109205": 1,
      "109209": 1,
      "109211": 1,
      "109216": 1,
      "109221": 1,
      "109222": 1,
      "109225": 1,
      "109227": 1,
      "109231": 1,
      "109239": 1,
      "109240": 1,
      "109243": 1,
      "109247": 1,
      "109250": 1,
      "109252": 1,
      "109253": 1,
      "109260": 1,
      "109263": 1,
      "109264": 1,
      "109271": 2,
      "109273": 1,
      "109275": 1,
      "109282": 1,
      "109285": 3,
      "109291": 1,
      "109292": 1,
      "109294": 2,
      "109302": 1,
      "109303": 1,
      "109304": 2,
      "109305": 3,
      "109310": 2,
      "109311": 1,
      "109319": 1,
      "109320": 1,
      "109322": 1,
      "109323": 1,
      "109324": 2,
      "109327": 2,
      "109328": 2,
      "109329": 1,
      "109330": 1,
      "109335": 1,
      "109336": 1,
      "109338": 1,
      "109339": 1,
      "109342": 1,
      "109343": 1,
      "109345": 1,
      "109350": 1,
      "109351": 1,
      "109353": 1,
      "109354": 1,
      "109355": 2,
      "109356": 1,
      "109361": 1,
      "109364": 1,
      "109366": 3,
      "109368": 1,
      "109369": 1,
      "109370": 1,
      "109371": 2,
      "109373": 1,
      "109375": 2,
      "109377": 1,
      "109379": 1,
      "109380": 2,
      "109381": 1,
      "109383": 1,
      "109384": 1,
      "109386": 2,
      "109387": 1,
      "109388": 2,
      "109389": 1,
      "109392": 1,
      "109394": 1,
      "109398": 2,
      "109401": 1,
      "109402": 1,
      "109406": 1,
      "109407": 1,
      "109409": 1,
      "109411": 1,
      "109412": 1,
      "109413": 2,
      "109414": 2,
      "109423": 1,
      "109425": 1,
      "109428": 3,
      "109430": 2,
      "109432": 1,
      "109440": 1,
      "109444": 1,
      "109449": 1,
      "109451": 1,
      "109454": 1,
      "109460": 1,
      "109462": 1,
      "109463": 1,
      "109466": 1,
      "109469": 1,
      "109474": 1,
      "109477": 2,
      "109479": 1,
      "109482": 2,
      "109486": 1,
      "109490": 1,
      "109492": 1,
      "109494": 1,
      "109497": 1,
      "109500": 1,
      "109502": 1,
      "109509": 1,
      "109512": 3,
      "109521": 2,
      "109526": 1,
      "109528": 1,
      "109535": 1,
      "109541": 1,
      "109543": 1,
      "109548": 1,
      "109549": 1,
      "109550": 1,
      "109551": 2,
      "109554": 1,
      "109555": 1,
      "109567": 1,
      "109569": 2,
      "109571": 2,
      "109577": 1,
      "109580": 1,
      "109581": 2,
      "109582": 1,
      "109583": 1,
      "109587": 1,
      "109597": 1,
      "109614": 1,
      "109616": 1,
      "109663": 1,
      "109693": 1,
      "109701": 1,
      "109748": 1,
      "109764": 1,
      "109797": 1,
      "109802": 1,
      "109870": 1,
      "109876": 1,
      "109900": 1,
      "109964": 1,
      "109967": 1,
      "110044": 1,
      "110080": 1,
      "110097": 1,
      "110134": 1,
      "110148": 1,
      "110217": 1,
      "110262": 1,
      "110263": 1,
      "110304": 1,
      "110341": 1,
      "110357": 1,
      "110396": 1,
      "110409": 1,
      "110460": 1,
      "110463": 1,
      "110464": 1,
      "110506": 1,
      "110513": 1,
      "110557": 1,
      "110565": 1,
      "110582": 1,
      "110624": 1,
      "110628": 1,
      "110650": 2,
      "110705": 1,
      "110707": 1,
      "110737": 1,
      "110771": 1,
      "110780": 1,
      "110820": 1,
      "110837": 1,
      "110848": 1,
      "110857": 1,
      "110882": 1,
      "110907": 1,
      "110924": 1,
      "110964": 1,
      "110972": 1,
      "110998": 1,
      "111009": 1,
      "111037": 2,
      "111075": 1,
      "111088": 1,
      "111107": 1,
      "111146": 1,
      "111153": 1,
      "111182": 1,
      "111196": 1,
      "111225": 1,
      "111241": 1,
      "111263": 1,
      "111270": 1,
      "111279": 1,
      "111325": 1,
      "111335": 1,
      "111340": 1,
      "111342": 1,
      "111386": 1,
      "111393": 1,
      "111410": 1,
      "111447": 1,
      "111460": 1,
      "111490": 1,
      "111499": 1,
      "111515": 1,
      "111518": 1,
      "111564": 1,
      "111567": 1,
      "111575": 1,
      "111589": 1,
      "111623": 1,
      "111633": 1,
      "111664": 1,
      "111680": 1,
      "111694": 1,
      "111728": 1,
      "111730": 1,
      "111731": 1,
      "111741": 1,
      "111778": 1,
      "111784": 1,
      "111802": 1,
      "111829": 2,
      "111866": 1,
      "111870": 1,
      "111893": 1,
      "111901": 1,
      "111929": 1,
      "111948": 1,
      "111957": 1,
      "111972": 1,
      "111980": 1,
      "112008": 1,
      "112031": 1,
      "112034": 1,
      "112054": 1,
      "112077": 1,
      "112091": 1,
      "112125": 2,
      "112142": 1,
      "112166": 1,
      "112193": 1,
      "112211": 1,
      "112219": 1,
      "112228": 1,
      "112280": 1,
      "112291": 1,
      "112293": 1,
      "112310": 1,
      "112340": 1,
      "112344": 1,
      "112349": 1,
      "112407": 1,
      "112431": 1,
      "112433": 1,
      "112448": 1,
      "112489": 1,
      "112511": 1,
      "112513": 1,
      "112515": 1,
      "112555": 1,
      "112577": 1,
      "112591": 1,
      "112593": 1,
      "112632": 1,
      "112633": 1,
      "112650": 1,
      "112675": 1,
      "112694": 1,
      "112700": 1,
      "112723": 1,
      "112748": 1,
      "112759": 1,
      "112800": 1,
      "112806": 1,
      "112816": 1,
      "112829": 1,
      "112855": 1,
      "112857": 1,
      "112864": 1,
      "112896": 1,
      "112921": 1,
      "112923": 1,
      "112935": 1,
      "112969": 1,
      "112975": 1,
      "112977": 1,
      "112986": 1,
      "112994": 1,
      "113003": 1,
      "113008": 1,
      "113023": 2,
      "113078": 1,
      "113115": 1,
      "113143": 1,
      "113145": 1,
      "113186": 1,
      "113241": 1,
      "113285": 1,
      "113309": 1,
      "113347": 1,
      "113377": 1,
      "113412": 1,
      "113424": 1,
      "113459": 1,
      "113505": 1,
      "113528": 1,
      "113564": 1,
      "113571": 1,
      "113625": 1,
      "113655": 1,
      "113693": 1,
      "113716": 1,
      "113718": 1,
      "113752": 1,
      "113763": 1,
      "113809": 1,
      "113816": 1,
      "113857": 1,
      "113872": 1,
      "113874": 1,
      "113888": 1,
      "113904": 1,
      "113922": 1,
      "113940": 1,
      "113945": 1,
      "113949": 1,
      "113953": 1,
      "113954": 1,
      "113961": 1,
      "113962": 1,
      "113963": 1,
      "113966": 1,
      "113973": 1,
      "113975": 2,
      "113976": 1,
      "113977": 1,
      "113978": 1,
      "113979": 1,
      "113988": 1,
      "113990": 1,
      "113991": 1,
      "113996": 1,
      "113999": 1,
      "114001": 1,
      "114002": 1,
      "114008": 1,
      "114009": 1,
      "114014": 1,
      "114024": 1,
      "114027": 2,
      "114028": 2,
      "114029": 1,
      "114030": 3,
      "114032": 2,
      "114037": 2,
      "114056": 2,
      "114058": 3,
      "114060": 1,
      "114062": 1,
      "114065": 2,
      "114066": 2,
      "114069": 1,
      "114073": 1,
      "114079": 1,
      "114082": 1,
      "114092": 1,
      "114099": 1,
      "114104": 1,
      "114112": 1,
      "114113": 1,
      "114114": 1,
      "114118": 1,
      "114120": 1,
      "114123": 1,
      "114128": 2,
      "114131": 1,
      "114136": 1,
      "114137": 2,
      "114148": 1,
      "114152": 1,
      "114156": 1,
      "114158": 2,
      "114164": 1,
      "114166": 1,
      "114169": 1,
      "114171": 1,
      "114178": 1,
      "114180": 1,
      "114193": 1,
      "114194": 1,
      "114196": 1,
      "114208": 1,
      "114210": 3,
      "114213": 1,
      "114221": 1,
      "114224": 1,
      "114231": 1,
      "114232": 1,
      "114235": 1,
      "114237": 1,
      "114241": 1,
      "114242": 1,
      "114244": 1,
      "114249": 1,
      "114252": 1,
      "114256": 1,
      "114259": 1,
      "114261": 1,
      "114264": 1,
      "114272": 2,
      "114279": 1,
      "114281": 2,
      "114287": 1,
      "114290": 1,
      "114295": 1,
      "114298": 1,
      "114299": 1,
      "114300": 1,
      "114302": 1,
      "114303": 1,
      "114307": 1,
      "114308": 1,
      "114312": 1,
      "114313": 2,
      "114316": 1,
      "114319": 1,
      "114321": 1,
      "114325": 1,
      "114327": 2,
      "114329": 1,
      "114335": 2,
      "114346": 2,
      "114347": 2,
      "114349": 1,
      "114352": 1,
      "114355": 1,
      "114357": 3,
      "114358": 1,
      "114359": 5,
      "114361": 2,
      "114362": 1,
      "114363": 3,
      "114364": 3,
      "114368": 2,
      "114371": 1,
      "114373": 1,
      "114375": 1,
      "114378": 2,
      "114381": 1,
      "114384": 1,
      "114386": 1,
      "114387": 1,
      "114390": 2,
      "114395": 1,
      "114396": 1,
      "114397": 2,
      "114399": 1,
      "114402": 2,
      "114406": 1,
      "114407": 2,
      "114408": 2,
      "114409": 1,
      "114410": 1,
      "114413": 1,
      "114414": 1,
      "114417": 1,
      "114420": 1,
      "114422": 1,
      "114424": 2,
      "114427": 1,
      "114428": 1,
      "114432": 2,
      "114435": 1,
      "114437": 1,
      "114440": 2,
      "114442": 2,
      "114445": 1,
      "114446": 1,
      "114448": 1,
      "114450": 1,
      "114455": 1,
      "114456": 2,
      "114457": 1,
      "114460": 2,
      "114462": 1,
      "114463": 1,
      "114467": 1,
      "114482": 1,
      "114492": 1,
      "114499": 1,
      "114502": 1,
      "114535": 1,
      "114550": 1,
      "114557": 1,
      "114584": 1,
      "114608": 1,
      "114613": 1,
      "114617": 1,
      "114632": 1,
      "114636": 1,
      "114639": 1,
      "114660": 1,
      "114661": 1,
      "114666": 1,
      "114671": 1,
      "114672": 1,
      "114683": 1,
      "114689": 1,
      "114690": 1,
      "114719": 1,
      "114720": 1,
      "114747": 1,
      "114753": 1,
      "114757": 1,
      "114759": 1,
      "114766": 1,
      "114767": 1,
      "114775": 1,
      "114777": 1,
      "114783": 1,
      "114804": 1,
      "114806": 1,
      "114823": 1,
      "114826": 1,
      "114842": 1,
      "114843": 1,
      "114847": 1,
      "114863": 1,
      "114878": 1,
      "114880": 2,
      "114883": 1,
      "114884": 1,
      "114889": 1,
      "114894": 1,
      "114896": 1,
      "114898": 1,
      "114900": 1,
      "114901": 3,
      "114902": 1,
      "114905": 2,
      "114906": 1,
      "114907": 2,
      "114908": 1,
      "114909": 2,
      "114910": 1,
      "114911": 1,
      "114912": 2,
      "114913": 3,
      "114914": 2,
      "114915": 1,
      "114917": 1,
      "114918": 3,
      "114920": 2,
      "114921": 2,
      "114922": 1,
      "114923": 2,
      "114924": 3,
      "114925": 5,
      "114926": 2,
      "114927": 2,
      "114928": 2,
      "114929": 2,
      "114930": 2,
      "114931": 2,
      "114933": 3,
      "114934": 4,
      "114937": 2,
      "114938": 5,
      "114939": 3,
      "114940": 1,
      "114941": 1,
      "114943": 2,
      "114944": 2,
      "114945": 1,
      "114946": 1,
      "114947": 1,
      "114948": 6,
      "114950": 1,
      "114952": 2,
      "114953": 1,
      "114954": 1,
      "114956": 1,
      "114959": 1,
      "114961": 2,
      "114965": 2,
      "114966": 2,
      "114967": 1,
      "114968": 2,
      "114969": 1,
      "114970": 1,
      "114971": 1,
      "114974": 1,
      "114975": 1,
      "114978": 1,
      "114979": 1,
      "114980": 2,
      "114982": 1,
      "114983": 1,
      "114986": 1,
      "114987": 3,
      "114988": 2,
      "114990": 1,
      "114991": 1,
      "114992": 1,
      "114994": 4,
      "114997": 1,
      "114999": 2,
      "115000": 2,
      "115001": 1,
      "115002": 1,
      "115005": 1,
      "115006": 1,
      "115008": 1,
      "115012": 1,
      "115015": 1
   },
   "wasClean": true,
   "wasCloseHandshakeTimeout": false,
   "wasNotCleanReason": null,
   "wasOpenHandshakeTimeout": false,
   "wasServerConnectionDropTimeout": false,
   "wirelog": [
      [
         "TO",
         [
            350,
            "474554202f20485454502f312e310d0a557365722d4167656e743a204175746f6261686e5465737453756974652f302e382e302d302e31302e390d0a486f7374 ..."
         ],
         false
      ],
      [
         "RO",
         [
            245,
            "485454502f312e312031303120537769746368696e672050726f746f636f6c730d0a557067726164653a20776562736f636b65740d0a436f6e6e656374696f6e ..."
         ]
      ],
      [
         "WLM",
         false
      ],
      [
         "TI",
         480
      ],
      [
         "WLM",
         true
      ],
      [
         "TF",
         [
            2,
            "0x03e8"
         ],
         8,
         true,
         0,
         "40fd8ac8",
         null,
         null,
         false
      ],
      [
         "TO",
         [
            8,
            "888240fd8ac84315"
         ],
         false
      ],
      [
         "RO",
         [
            4,
            "880203e8"
         ]
      ],
      [
         "RF",
         [
            2,
            "0x03e8"
         ],
         8,
         true,
         0,
         false,
         null
      ]
   ]
}