{
   "agent": "RatchetRFC/0.1.0",
   "behavior": "OK",
   "behaviorClose": "OK",
   "case": 355,
   "closedByMe": true,
   "createStats": true,
   "createWirelog": true,
   "description": "Send 1000 compressed messages each of payload size 131072, auto-fragment to 1024 octets. Use default permessage-deflate offer.",
   "droppedByMe": false,
   "duration": 21575,
   "expectation": "Receive echo'ed messages (with payload as sent). Timeout case after 480 secs.",
   "expected": {},
   "expectedClose": {
      "closeCode": [
         1000
      ],
      "closedByMe": true,
      "requireClean": true
   },
   "failedByMe": false,
   "httpRequest": "GET / HTTP/1.1\r\nUser-Agent: AutobahnTestSuite/0.8.0-0.10.9\r\nHost: host.ratchet.internal:9001\r\nUpgrade: WebSocket\r\nConnection: Upgrade\r\nPragma: no-cache\r\nCache-Control: no-cache\r\nSec-WebSocket-Key: BJsa/F2WcpO1PGO5EN4UKA==\r\nSec-WebSocket-Extensions: permessage-deflate; client_no_context_takeover; client_max_window_bits\r\nSec-WebSocket-Version: 13\r\n\r\n",
   "httpResponse": "HTTP/1.1 101 Switching Protocols\r\nUpgrade: websocket\r\nConnection: Upgrade\r\nSec-WebSocket-Accept: hljReM1hSqTZmDmUCDLM6ozG4qI=\r\nX-Powered-By: Ratchet\r\nSec-Websocket-Extensions: permessage-deflate; client_no_context_takeover\r\nContent-Length: 0\r\n\r\n",
   "id": "12.3.16",
   "isServer": false,
   "localCloseCode": 1000,
   "localCloseReason": null,
   "received": [],
   "remoteCloseCode": 1000,
   "remoteCloseReason": null,
   "reportCompressionRatio": true,
   "reportTime": true,
   "result": "Ok, received all echo'ed messages in time.",
   "resultClose": "Connection was properly closed",
   "rxFrameStats": {
      "2": 1000,
      "8": 1
   },
   "rxOctetStats": {
      "3": 1,
      "4": 1,
      "75": 1,
      "112": 1,
      "145": 1,
      "148": 1,
      "154": 1,
      "195": 1,
      "245": 1,
      "258": 1,
      "288": 1,
      "315": 1,
      "338": 1,
      "372": 1,
      "385": 1,
      "420": 1,
      "439": 1,
      "479": 1,
      "584": 1,
      "895": 1,
      "934": 1,
      "1070": 1,
      "1073": 1,
      "1105": 1,
      "1119": 1,
      "1169": 1,
      "1320": 1,
      "1338": 1,
      "1388": 1,
      "1446": 1,
      "1460": 24,
      "1486": 1,
      "1498": 1,
      "1514": 1,
      "1530": 1,
      "1560": 1,
      "1577": 1,
      "1585": 1,
      "1645": 1,
      "1646": 1,
      "1692": 1,
      "1704": 1,
      "1754": 1,
      "1805": 1,
      "1814": 1,
      "1832": 1,
      "1859": 1,
      "1888": 1,
      "1890": 1,
      "1892": 1,
      "1920": 1,
      "1960": 1,
      "1978": 1,
      "2057": 1,
      "2110": 1,
      "2111": 1,
      "2115": 1,
      "2185": 1,
      "2192": 1,
      "2235": 1,
      "2264": 1,
      "2290": 1,
      "2297": 1,
      "2347": 1,
      "2352": 1,
      "2429": 1,
      "2432": 1,
      "2437": 1,
      "2456": 1,
      "2475": 1,
      "2484": 1,
      "2507": 1,
      "2527": 1,
      "2532": 1,
      "2564": 2,
      "2587": 1,
      "2638": 1,
      "2650": 1,
      "2651": 1,
      "2654": 1,
      "2729": 1,
      "2739": 1,
      "2747": 1,
      "2759": 1,
      "2776": 1,
      "2811": 2,
      "2814": 1,
      "2822": 1,
      "2848": 1,
      "2861": 1,
      "2920": 20,
      "2924": 1,
      "2930": 1,
      "2985": 1,
      "3060": 1,
      "3064": 1,
      "3069": 1,
      "3070": 1,
      "3101": 1,
      "3135": 1,
      "3207": 1,
      "3209": 1,
      "3252": 1,
      "3264": 1,
      "3277": 1,
      "3282": 1,
      "3287": 1,
      "3302": 1,
      "3307": 1,
      "3325": 1,
      "3330": 1,
      "3333": 1,
      "3356": 1,
      "3392": 1,
      "3399": 1,
      "3441": 1,
      "3455": 1,
      "3486": 1,
      "3492": 1,
      "3526": 1,
      "3535": 1,
      "3582": 1,
      "3586": 1,
      "3618": 1,
      "3669": 1,
      "3677": 1,
      "3687": 1,
      "3707": 1,
      "3733": 1,
      "3738": 1,
      "3786": 1,
      "3796": 1,
      "3827": 1,
      "3848": 1,
      "3926": 1,
      "3950": 1,
      "3951": 1,
      "4011": 1,
      "4169": 1,
      "4197": 1,
      "4238": 1,
      "4261": 1,
      "4270": 1,
      "4274": 1,
      "4306": 1,
      "4313": 1,
      "4315": 1,
      "4316": 1,
      "4343": 1,
      "4380": 18,
      "4390": 1,
      "4392": 1,
      "4399": 1,
      "4413": 1,
      "4422": 1,
      "4438": 1,
      "4444": 1,
      "4466": 1,
      "4467": 1,
      "4473": 1,
      "4485": 1,
      "4502": 1,
      "4510": 1,
      "4533": 1,
      "4541": 1,
      "4554": 1,
      "4564": 1,
      "4588": 1,
      "4592": 1,
      "4635": 1,
      "4652": 1,
      "4675": 1,
      "4726": 1,
      "4737": 1,
      "4745": 1,
      "4766": 1,
      "4804": 1,
      "4810": 1,
      "4833": 1,
      "4844": 1,
      "4868": 1,
      "4899": 1,
      "4933": 1,
      "4973": 1,
      "5018": 1,
      "5040": 1,
      "5041": 1,
      "5054": 1,
      "5056": 1,
      "5063": 1,
      "5111": 1,
      "5288": 1,
      "5316": 1,
      "5362": 1,
      "5387": 1,
      "5403": 1,
      "5406": 1,
      "5453": 1,
      "5479": 1,
      "5519": 1,
      "5520": 1,
      "5534": 1,
      "5570": 1,
      "5581": 1,
      "5584": 1,
      "5628": 1,
      "5651": 1,
      "5656": 1,
      "5687": 1,
      "5690": 1,
      "5745": 1,
      "5764": 1,
      "5769": 1,
      "5770": 1,
      "5772": 1,
      "5778": 1,
      "5779": 1,
      "5796": 1,
      "5840": 34,
      "5860": 1,
      "5872": 1,
      "5882": 1,
      "5906": 1,
      "5915": 1,
      "5983": 1,
      "5996": 1,
      "6003": 1,
      "6025": 1,
      "6031": 1,
      "6085": 1,
      "6091": 1,
      "6104": 1,
      "6144": 1,
      "6150": 1,
      "6164": 1,
      "6174": 2,
      "6231": 1,
      "6274": 1,
      "6308": 1,
      "6336": 1,
      "6340": 1,
      "6377": 1,
      "6396": 1,
      "6435": 1,
      "6448": 1,
      "6508": 1,
      "6529": 1,
      "6530": 1,
      "6532": 1,
      "6548": 1,
      "6636": 1,
      "6665": 1,
      "6773": 1,
      "6784": 1,
      "6817": 1,
      "6833": 1,
      "6835": 1,
      "6845": 1,
      "6847": 1,
      "6859": 1,
      "6867": 1,
      "6870": 1,
      "6911": 1,
      "6926": 1,
      "6944": 1,
      "6965": 1,
      "6996": 1,
      "7017": 1,
      "7056": 1,
      "7061": 1,
      "7084": 1,
      "7110": 1,
      "7128": 1,
      "7136": 1,
      "7180": 1,
      "7201": 1,
      "7233": 1,
      "7255": 2,
      "7258": 1,
      "7286": 1,
      "7292": 1,
      "7300": 39,
      "7318": 1,
      "7337": 2,
      "7338": 1,
      "7369": 1,
      "7378": 1,
      "7402": 1,
      "7414": 1,
      "7440": 2,
      "7462": 1,
      "7470": 1,
      "7516": 1,
      "7527": 1,
      "7555": 1,
      "7589": 1,
      "7592": 1,
      "7653": 1,
      "7661": 1,
      "7666": 1,
      "7682": 1,
      "7717": 1,
      "7723": 1,
      "7751": 1,
      "7776": 1,
      "7782": 1,
      "7807": 1,
      "7894": 1,
      "7928": 1,
      "7937": 1,
      "7958": 1,
      "7991": 1,
      "8040": 1,
      "8101": 1,
      "8112": 1,
      "8123": 1,
      "8132": 1,
      "8168": 1,
      "8171": 1,
      "8186": 1,
      "8192": 1,
      "8201": 1,
      "8204": 1,
      "8242": 1,
      "8262": 1,
      "8284": 1,
      "8302": 1,
      "8303": 1,
      "8324": 1,
      "8341": 1,
      "8376": 1,
      "8415": 1,
      "8427": 1,
      "8446": 1,
      "8458": 1,
      "8469": 1,
      "8479": 1,
      "8509": 1,
      "8519": 1,
      "8534": 1,
      "8548": 1,
      "8572": 1,
      "8578": 1,
      "8582": 1,
      "8638": 1,
      "8643": 1,
      "8650": 1,
      "8664": 1,
      "8681": 1,
      "8702": 1,
      "8706": 1,
      "8728": 1,
      "8760": 61,
      "8761": 1,
      "8771": 1,
      "8773": 1,
      "8780": 1,
      "8784": 1,
      "8789": 1,
      "8803": 1,
      "8834": 1,
      "8839": 1,
      "8840": 1,
      "8872": 1,
      "8893": 1,
      "8913": 1,
      "8929": 1,
      "8953": 1,
      "8966": 1,
      "8977": 1,
      "8996": 1,
      "9000": 1,
      "9015": 1,
      "9097": 1,
      "9100": 1,
      "9107": 1,
      "9169": 1,
      "9208": 1,
      "9248": 1,
      "9255": 1,
      "9346": 1,
      "9367": 1,
      "9388": 1,
      "9416": 1,
      "9442": 1,
      "9446": 1,
      "9483": 1,
      "9520": 1,
      "9580": 1,
      "9606": 1,
      "9611": 1,
      "9633": 1,
      "9639": 1,
      "9652": 1,
      "9679": 1,
      "9687": 1,
      "9700": 1,
      "9708": 1,
      "9720": 1,
      "9760": 1,
      "9775": 1,
      "9794": 1,
      "9795": 1,
      "9797": 1,
      "9809": 1,
      "9815": 1,
      "9819": 1,
      "9827": 1,
      "9834": 1,
      "9857": 1,
      "9871": 1,
      "9872": 1,
      "9902": 1,
      "9921": 1,
      "9934": 1,
      "9942": 1,
      "9957": 1,
      "9970": 1,
      "9989": 1,
      "9994": 1,
      "10046": 1,
      "10050": 1,
      "10071": 1,
      "10077": 1,
      "10090": 1,
      "10173": 1,
      "10184": 1,
      "10185": 1,
      "10201": 1,
      "10220": 73,
      "10240": 1,
      "10245": 1,
      "10253": 1,
      "10268": 1,
      "10277": 1,
      "10287": 1,
      "10296": 1,
      "10303": 1,
      "10304": 1,
      "10308": 1,
      "10310": 1,
      "10314": 1,
      "10327": 1,
      "10333": 1,
      "10343": 1,
      "10359": 1,
      "10371": 1,
      "10374": 1,
      "10400": 1,
      "10418": 1,
      "10419": 1,
      "10422": 1,
      "10426": 1,
      "10429": 2,
      "10433": 2,
      "10434": 1,
      "10488": 1,
      "10505": 1,
      "10526": 1,
      "10527": 1,
      "10529": 1,
      "10541": 1,
      "10584": 1,
      "10646": 1,
      "10727": 1,
      "10753": 1,
      "10769": 1,
      "10803": 1,
      "10821": 1,
      "10828": 1,
      "10845": 1,
      "10876": 1,
      "10882": 1,
      "10908": 1,
      "10911": 1,
      "10917": 1,
      "10923": 1,
      "11022": 1,
      "11077": 1,
      "11088": 1,
      "11164": 1,
      "11170": 1,
      "11173": 1,
      "11201": 1,
      "11267": 1,
      "11312": 1,
      "11331": 1,
      "11360": 1,
      "11370": 1,
      "11375": 1,
      "11420": 1,
      "11453": 1,
      "11476": 1,
      "11520": 1,
      "11537": 1,
      "11578": 1,
      "11581": 1,
      "11586": 1,
      "11588": 1,
      "11599": 1,
      "11613": 1,
      "11633": 1,
      "11640": 1,
      "11642": 1,
      "11646": 1,
      "11654": 1,
      "11680": 123,
      "11752": 1,
      "11794": 1,
      "11808": 1,
      "11811": 1,
      "11838": 1,
      "11844": 1,
      "11848": 1,
      "11852": 1,
      "11869": 1,
      "11875": 1,
      "11881": 1,
      "11882": 1,
      "11893": 1,
      "11894": 1,
      "11897": 1,
      "11910": 1,
      "11937": 1,
      "11960": 1,
      "11968": 1,
      "11971": 1,
      "12005": 1,
      "12007": 1,
      "12008": 1,
      "12028": 1,
      "12037": 1,
      "12042": 1,
      "12054": 1,
      "12066": 1,
      "12076": 1,
      "12082": 1,
      "12091": 1,
      "12095": 2,
      "12117": 1,
      "12129": 1,
      "12145": 1,
      "12148": 1,
      "12167": 1,
      "12196": 1,
      "12201": 1,
      "12202": 1,
      "12230": 1,
      "12246": 1,
      "12251": 1,
      "12385": 1,
      "12458": 1,
      "12461": 1,
      "12484": 1,
      "12501": 1,
      "12527": 1,
      "12547": 1,
      "12571": 1,
      "12583": 1,
      "12599": 1,
      "12613": 1,
      "12676": 1,
      "12718": 1,
      "12731": 1,
      "12736": 1,
      "12737": 1,
      "12742": 1,
      "12788": 1,
      "12792": 1,
      "12807": 1,
      "12834": 1,
      "12842": 1,
      "12860": 1,
      "12863": 1,
      "12876": 1,
      "12933": 1,
      "12939": 2,
      "12967": 1,
      "12972": 1,
      "13001": 1,
      "13018": 1,
      "13037": 1,
      "13049": 1,
      "13054": 1,
      "13111": 1,
      "13140": 100,
      "13184": 1,
      "13215": 1,
      "13216": 1,
      "13220": 2,
      "13222": 1,
      "13234": 1,
      "13235": 1,
      "13236": 1,
      "13253": 1,
      "13257": 1,
      "13262": 1,
      "13263": 1,
      "13273": 1,
      "13317": 1,
      "13356": 1,
      "13378": 1,
      "13379": 1,
      "13384": 1,
      "13389": 1,
      "13392": 2,
      "13458": 1,
      "13459": 1,
      "13526": 1,
      "13629": 2,
      "13633": 1,
      "13645": 1,
      "13665": 1,
      "13701": 1,
      "13706": 1,
      "13707": 1,
      "13721": 1,
      "13734": 1,
      "13739": 1,
      "13743": 1,
      "13768": 1,
      "13791": 1,
      "13835": 1,
      "13840": 1,
      "13947": 1,
      "13981": 1,
      "13995": 1,
      "14003": 1,
      "14033": 1,
      "14051": 1,
      "14074": 1,
      "14091": 1,
      "14228": 1,
      "14270": 1,
      "14277": 1,
      "14297": 1,
      "14356": 1,
      "14358": 1,
      "14386": 1,
      "14392": 1,
      "14401": 1,
      "14404": 1,
      "14446": 1,
      "14474": 1,
      "14488": 1,
      "14516": 1,
      "14519": 1,
      "14556": 1,
      "14584": 1,
      "14592": 1,
      "14595": 1,
      "14600": 89,
      "14605": 1,
      "14672": 1,
      "14691": 1,
      "14744": 2,
      "14774": 1,
      "14792": 1,
      "14796": 1,
      "14812": 1,
      "14867": 1,
      "14928": 1,
      "14929": 1,
      "14945": 1,
      "14965": 1,
      "14985": 1,
      "15014": 1,
      "15083": 1,
      "15091": 1,
      "15108": 1,
      "15120": 1,
      "15124": 1,
      "15171": 1,
      "15178": 1,
      "15181": 1,
      "15202": 1,
      "15207": 2,
      "15213": 1,
      "15245": 1,
      "15264": 1,
      "15277": 1,
      "15289": 1,
      "15297": 1,
      "15317": 1,
      "15336": 1,
      "15339": 1,
      "15369": 1,
      "15387": 1,
      "15414": 1,
      "15417": 1,
      "15492": 1,
      "15545": 1,
      "15563": 1,
      "15564": 2,
      "15582": 1,
      "15640": 1,
      "15650": 1,
      "15651": 1,
      "15669": 1,
      "15677": 1,
      "15705": 1,
      "15713": 1,
      "15719": 1,
      "15750": 1,
      "15774": 1,
      "15795": 1,
      "15798": 1,
      "15816": 2,
      "15900": 1,
      "15941": 1,
      "15953": 1,
      "16015": 1,
      "16033": 1,
      "16049": 1,
      "16055": 1,
      "16058": 1,
      "16060": 87,
      "16070": 1,
      "16076": 1,
      "16109": 1,
      "16142": 1,
      "16150": 1,
      "16155": 1,
      "16166": 1,
      "16193": 2,
      "16202": 1,
      "16241": 1,
      "16244": 1,
      "16246": 1,
      "16275": 1,
      "16292": 1,
      "16298": 1,
      "16334": 1,
      "16340": 1,
      "16357": 1,
      "16393": 1,
      "16396": 1,
      "16405": 2,
      "16409": 1,
      "16422": 3,
      "16474": 1,
      "16495": 1,
      "16517": 1,
      "16520": 1,
      "16549": 1,
      "16550": 1,
      "16552": 1,
      "16584": 1,
      "16595": 1,
      "16622": 1,
      "16645": 1,
      "16679": 1,
      "16681": 1,
      "16702": 1,
      "16783": 1,
      "16789": 1,
      "16808": 1,
      "16840": 1,
      "16918": 1,
      "16932": 1,
      "16940": 1,
      "16979": 1,
      "16985": 1,
      "16997": 1,
      "17011": 1,
      "17012": 1,
      "17043": 1,
      "17069": 1,
      "17090": 1,
      "17093": 1,
      "17138": 1,
      "17177": 1,
      "17183": 1,
      "17224": 1,
      "17228": 1,
      "17243": 1,
      "17268": 1,
      "17276": 5,
      "17288": 1,
      "17340": 2,
      "17361": 1,
      "17370": 1,
      "17391": 1,
      "17474": 1,
      "17498": 1,
      "17500": 1,
      "17520": 104,
      "17532": 1,
      "17544": 1,
      "17571": 1,
      "17583": 1,
      "17593": 1,
      "17644": 1,
      "17671": 1,
      "17676": 1,
      "17693": 1,
      "17719": 1,
      "17733": 1,
      "17757": 1,
      "17758": 1,
      "17768": 1,
      "17772": 1,
      "17775": 1,
      "17779": 1,
      "17809": 1,
      "17821": 1,
      "17851": 1,
      "17863": 1,
      "17935": 1,
      "17986": 1,
      "17996": 1,
      "17999": 1,
      "18027": 1,
      "18042": 1,
      "18105": 1,
      "18118": 1,
      "18139": 1,
      "18154": 1,
      "18258": 1,
      "18268": 1,
      "18299": 1,
      "18337": 1,
      "18348": 1,
      "18502": 1,
      "18528": 1,
      "18540": 1,
      "18561": 1,
      "18578": 1,
      "18596": 1,
      "18607": 1,
      "18615": 1,
      "18632": 1,
      "18640": 1,
      "18645": 1,
      "18658": 1,
      "18736": 9,
      "18737": 1,
      "18752": 2,
      "18792": 1,
      "18798": 1,
      "18812": 1,
      "18824": 1,
      "18826": 1,
      "18832": 1,
      "18836": 1,
      "18881": 1,
      "18882": 1,
      "18904": 1,
      "18908": 1,
      "18914": 1,
      "18942": 1,
      "18944": 1,
      "18946": 1,
      "18947": 1,
      "18980": 75,
      "19017": 1,
      "19048": 1,
      "19060": 1,
      "19085": 1,
      "19118": 1,
      "19129": 1,
      "19132": 1,
      "19164": 1,
      "19172": 1,
      "19195": 1,
      "19201": 1,
      "19212": 1,
      "19261": 1,
      "19281": 1,
      "19282": 1,
      "19325": 1,
      "19348": 1,
      "19356": 1,
      "19409": 1,
      "19425": 1,
      "19446": 1,
      "19498": 1,
      "19527": 1,
      "19593": 2,
      "19616": 1,
      "19638": 1,
      "19648": 1,
      "19676": 1,
      "19690": 1,
      "19691": 1,
      "19715": 1,
      "19754": 1,
      "19798": 1,
      "19802": 2,
      "19811": 1,
      "19829": 1,
      "19910": 1,
      "19920": 1,
      "19949": 1,
      "19961": 1,
      "20001": 1,
      "20143": 1,
      "20150": 1,
      "20159": 1,
      "20170": 1,
      "20176": 1,
      "20190": 1,
      "20196": 7,
      "20206": 1,
      "20214": 1,
      "20263": 1,
      "20264": 1,
      "20273": 1,
      "20317": 1,
      "20320": 1,
      "20322": 1,
      "20338": 1,
      "20360": 1,
      "20387": 1,
      "20403": 1,
      "20423": 1,
      "20429": 1,
      "20432": 1,
      "20440": 54,
      "20449": 1,
      "20479": 1,
      "20502": 1,
      "20515": 1,
      "20520": 1,
      "20540": 1,
      "20541": 1,
      "20552": 1,
      "20558": 1,
      "20584": 1,
      "20594": 1,
      "20673": 1,
      "20773": 1,
      "20777": 1,
      "20778": 1,
      "20805": 1,
      "20812": 1,
      "20823": 1,
      "20833": 1,
      "20867": 1,
      "20874": 1,
      "20876": 2,
      "20884": 1,
      "20908": 1,
      "20938": 1,
      "20944": 1,
      "20958": 1,
      "20979": 1,
      "21012": 1,
      "21041": 1,
      "21094": 1,
      "21151": 1,
      "21180": 1,
      "21181": 1,
      "21206": 1,
      "21271": 2,
      "21316": 1,
      "21338": 1,
      "21356": 1,
      "21366": 1,
      "21411": 1,
      "21422": 1,
      "21430": 1,
      "21435": 1,
      "21483": 1,
      "21498": 1,
      "21519": 1,
      "21520": 1,
      "21522": 1,
      "21523": 1,
      "21537": 1,
      "21566": 1,
      "21571": 1,
      "21596": 1,
      "21601": 1,
      "21626": 1,
      "21656": 6,
      "21670": 1,
      "21701": 1,
      "21702": 1,
      "21749": 1,
      "21758": 1,
      "21780": 1,
      "21803": 1,
      "21825": 1,
      "21846": 1,
      "21848": 1,
      "21878": 1,
      "21896": 2,
      "21900": 62,
      "21921": 1,
      "21926": 1,
      "21927": 1,
      "21959": 1,
      "21962": 1,
      "21970": 1,
      "22025": 1,
      "22046": 1,
      "22050": 1,
      "22071": 1,
      "22102": 1,
      "22109": 1,
      "22112": 1,
      "22127": 1,
      "22138": 1,
      "22163": 1,
      "22190": 1,
      "22209": 1,
      "22232": 1,
      "22257": 1,
      "22270": 1,
      "22277": 1,
      "22320": 1,
      "22336": 1,
      "22339": 1,
      "22387": 1,
      "22392": 1,
      "22414": 2,
      "22427": 1,
      "22485": 1,
      "22508": 1,
      "22514": 1,
      "22630": 1,
      "22700": 1,
      "22706": 1,
      "22824": 1,
      "22858": 1,
      "22887": 1,
      "22890": 1,
      "22922": 1,
      "22923": 1,
      "22936": 1,
      "22949": 1,
      "22979": 1,
      "22984": 1,
      "23004": 1,
      "23015": 1,
      "23016": 1,
      "23062": 1,
      "23083": 1,
      "23106": 1,
      "23116": 6,
      "23153": 1,
      "23218": 1,
      "23226": 1,
      "23232": 1,
      "23240": 1,
      "23271": 1,
      "23282": 1,
      "23299": 1,
      "23305": 1,
      "23350": 1,
      "23360": 55,
      "23395": 1,
      "23430": 1,
      "23440": 6,
      "23450": 1,
      "23454": 1,
      "23473": 1,
      "23487": 1,
      "23494": 1,
      "23509": 1,
      "23623": 1,
      "23635": 1,
      "23650": 1,
      "23652": 1,
      "23708": 1,
      "23781": 1,
      "23850": 1,
      "23854": 1,
      "23934": 1,
      "23965": 1,
      "24001": 1,
      "24032": 1,
      "24050": 1,
      "24055": 1,
      "24078": 1,
      "24103": 1,
      "24110": 1,
      "24180": 1,
      "24191": 1,
      "24219": 1,
      "24241": 1,
      "24257": 1,
      "24265": 1,
      "24299": 1,
      "24304": 1,
      "24312": 1,
      "24326": 1,
      "24338": 1,
      "24349": 1,
      "24388": 1,
      "24441": 1,
      "24465": 1,
      "24547": 2,
      "24566": 1,
      "24576": 16,
      "24617": 1,
      "24638": 1,
      "24667": 1,
      "24673": 1,
      "24675": 1,
      "24693": 1,
      "24702": 1,
      "24796": 1,
      "24808": 1,
      "24820": 44,
      "24824": 1,
      "24832": 1,
      "24836": 1,
      "24848": 2,
      "24863": 1,
      "24900": 1,
      "24903": 1,
      "24906": 1,
      "24917": 1,
      "24927": 1,
      "24936": 1,
      "24970": 1,
      "24971": 1,
      "24975": 1,
      "24976": 1,
      "24984": 1,
      "25008": 1,
      "25039": 1,
      "25046": 1,
      "25109": 1,
      "25122": 1,
      "25153": 1,
      "25163": 1,
      "25223": 1,
      "25248": 1,
      "25255": 1,
      "25268": 1,
      "25279": 1,
      "25310": 1,
      "25338": 1,
      "25421": 1,
      "25453": 1,
      "25455": 1,
      "25556": 1,
      "25580": 1,
      "25603": 1,
      "25618": 1,
      "25637": 1,
      "25672": 1,
      "25686": 1,
      "25702": 1,
      "25709": 2,
      "25712": 1,
      "25729": 1,
      "25744": 1,
      "25768": 1,
      "25779": 1,
      "25798": 1,
      "25811": 1,
      "25827": 1,
      "25853": 1,
      "25861": 1,
      "25896": 1,
      "25921": 1,
      "25926": 1,
      "25944": 1,
      "25954": 1,
      "25961": 1,
      "25984": 1,
      "26036": 8,
      "26076": 1,
      "26081": 1,
      "26130": 1,
      "26169": 1,
      "26191": 1,
      "26210": 1,
      "26246": 1,
      "26266": 1,
      "26280": 43,
      "26281": 1,
      "26339": 2,
      "26346": 1,
      "26358": 1,
      "26360": 6,
      "26379": 1,
      "26396": 1,
      "26410": 1,
      "26420": 1,
      "26439": 1,
      "26465": 1,
      "26470": 1,
      "26471": 1,
      "26472": 2,
      "26486": 1,
      "26489": 1,
      "26509": 1,
      "26518": 1,
      "26525": 1,
      "26532": 1,
      "26537": 1,
      "26603": 1,
      "26620": 1,
      "26633": 1,
      "26668": 1,
      "26727": 1,
      "26739": 1,
      "26790": 1,
      "26799": 1,
      "26812": 1,
      "26863": 1,
      "26902": 1,
      "26924": 1,
      "26983": 1,
      "27009": 1,
      "27076": 1,
      "27097": 1,
      "27140": 1,
      "27156": 1,
      "27167": 1,
      "27190": 1,
      "27204": 1,
      "27262": 1,
      "27285": 1,
      "27301": 1,
      "27302": 1,
      "27304": 1,
      "27305": 1,
      "27317": 1,
      "27364": 1,
      "27367": 1,
      "27373": 1,
      "27388": 1,
      "27416": 1,
      "27420": 1,
      "27460": 1,
      "27482": 1,
      "27496": 4,
      "27534": 1,
      "27540": 1,
      "27542": 1,
      "27580": 1,
      "27596": 1,
      "27625": 1,
      "27629": 1,
      "27633": 1,
      "27642": 1,
      "27646": 1,
      "27655": 1,
      "27740": 24,
      "27762": 1,
      "27768": 1,
      "27787": 1,
      "27820": 10,
      "27826": 1,
      "27849": 1,
      "27865": 1,
      "27869": 1,
      "27892": 1,
      "27901": 1,
      "27963": 1,
      "27973": 1,
      "28043": 1,
      "28059": 1,
      "28109": 1,
      "28133": 1,
      "28147": 1,
      "28148": 1,
      "28214": 1,
      "28218": 1,
      "28221": 1,
      "28233": 1,
      "28245": 1,
      "28259": 1,
      "28280": 1,
      "28300": 1,
      "28335": 1,
      "28345": 1,
      "28360": 1,
      "28362": 1,
      "28429": 1,
      "28441": 1,
      "28453": 1,
      "28484": 1,
      "28487": 2,
      "28501": 1,
      "28509": 2,
      "28568": 1,
      "28693": 1,
      "28708": 1,
      "28751": 1,
      "28754": 1,
      "28765": 1,
      "28776": 1,
      "28789": 2,
      "28819": 1,
      "28868": 1,
      "28910": 1,
      "28937": 2,
      "28956": 9,
      "28958": 1,
      "28964": 1,
      "29011": 1,
      "29019": 1,
      "29065": 1,
      "29074": 1,
      "29103": 2,
      "29108": 1,
      "29119": 1,
      "29131": 1,
      "29135": 1,
      "29200": 32,
      "29234": 1,
      "29280": 3,
      "29282": 1,
      "29302": 1,
      "29316": 1,
      "29346": 1,
      "29356": 1,
      "29357": 1,
      "29370": 1,
      "29376": 1,
      "29382": 1,
      "29387": 1,
      "29414": 1,
      "29420": 1,
      "29437": 1,
      "29453": 1,
      "29462": 1,
      "29538": 1,
      "29547": 1,
      "29566": 1,
      "29595": 1,
      "29617": 1,
      "29624": 1,
      "29625": 1,
      "29665": 1,
      "29668": 1,
      "29670": 1,
      "29730": 1,
      "29800": 1,
      "29888": 1,
      "29904": 1,
      "29906": 1,
      "29912": 1,
      "29982": 1,
      "30028": 1,
      "30072": 1,
      "30233": 1,
      "30235": 1,
      "30416": 2,
      "30426": 1,
      "30462": 1,
      "30493": 1,
      "30529": 1,
      "30546": 1,
      "30586": 1,
      "30589": 1,
      "30653": 1,
      "30657": 1,
      "30660": 19,
      "30663": 1,
      "30710": 1,
      "30717": 1,
      "30727": 1,
      "30728": 1,
      "30730": 1,
      "30736": 1,
      "30740": 1,
      "30791": 1,
      "30809": 1,
      "30811": 1,
      "30818": 1,
      "30820": 1,
      "30846": 1,
      "30877": 1,
      "30896": 1,
      "30941": 1,
      "30990": 1,
      "31021": 1,
      "31080": 1,
      "31083": 1,
      "31125": 1,
      "31184": 1,
      "31225": 1,
      "31302": 1,
      "31329": 1,
      "31348": 1,
      "31363": 1,
      "31382": 1,
      "31386": 1,
      "31403": 1,
      "31458": 1,
      "31521": 1,
      "31558": 1,
      "31569": 1,
      "31581": 1,
      "31587": 1,
      "31628": 1,
      "31670": 1,
      "31674": 1,
      "31678": 1,
      "31699": 1,
      "31704": 1,
      "31757": 1,
      "31760": 1,
      "31771": 1,
      "31774": 1,
      "31779": 1,
      "31824": 1,
      "31825": 1,
      "31826": 1,
      "31834": 1,
      "31839": 1,
      "31851": 1,
      "31876": 4,
      "31887": 1,
      "31917": 1,
      "32000": 1,
      "32024": 1,
      "32037": 1,
      "32075": 1,
      "32094": 1,
      "32106": 1,
      "32120": 17,
      "32124": 1,
      "32157": 1,
      "32173": 1,
      "32175": 1,
      "32200": 3,
      "32207": 1,
      "32214": 1,
      "32239": 1,
      "32245": 1,
      "32260": 1,
      "32292": 1,
      "32299": 1,
      "32334": 2,
      "32349": 1,
      "32357": 1,
      "32378": 1,
      "32383": 1,
      "32392": 1,
      "32399": 1,
      "32404": 1,
      "32417": 1,
      "32519": 1,
      "32602": 1,
      "32629": 1,
      "32651": 1,
      "32674": 1,
      "32700": 1,
      "32712": 1,
      "32714": 1,
      "32783": 1,
      "32803": 1,
      "32893": 1,
      "32926": 1,
      "32975": 1,
      "32995": 1,
      "33034": 1,
      "33126": 1,
      "33162": 1,
      "33165": 1,
      "33223": 1,
      "33224": 1,
      "33263": 1,
      "33267": 1,
      "33284": 1,
      "33300": 1,
      "33329": 1,
      "33336": 3,
      "33343": 1,
      "33366": 1,
      "33398": 1,
      "33513": 1,
      "33522": 1,
      "33560": 1,
      "33580": 8,
      "33595": 1,
      "33660": 6,
      "33687": 1,
      "33717": 1,
      "33740": 1,
      "33745": 1,
      "33781": 1,
      "33791": 1,
      "33810": 1,
      "33826": 1,
      "33847": 1,
      "33854": 1,
      "33866": 1,
      "33881": 1,
      "33915": 1,
      "33987": 1,
      "34116": 1,
      "34135": 1,
      "34173": 1,
      "34199": 1,
      "34265": 1,
      "34367": 1,
      "34395": 1,
      "34413": 1,
      "34530": 1,
      "34587": 1,
      "34689": 1,
      "34771": 1,
      "34796": 3,
      "34834": 1,
      "34864": 1,
      "34983": 1,
      "35005": 1,
      "35040": 4,
      "35120": 3,
      "35124": 1,
      "35199": 1,
      "35232": 1,
      "35363": 1,
      "35366": 1,
      "35367": 1,
      "35370": 1,
      "35433": 1,
      "35503": 1,
      "35603": 1,
      "35677": 1,
      "35788": 1,
      "35854": 1,
      "36013": 1,
      "36145": 1,
      "36206": 1,
      "36256": 1,
      "36489": 1,
      "36500": 2,
      "36586": 1,
      "36592": 1,
      "36639": 1,
      "36794": 1,
      "36873": 1,
      "36914": 1,
      "36974": 1,
      "37287": 1,
      "37958": 1,
      "37960": 2,
      "38074": 1,
      "38117": 1,
      "38235": 1,
      "38472": 1,
      "38584": 1,
      "38589": 1,
      "38885": 1,
      "39105": 1,
      "39404": 1,
      "39436": 1,
      "39516": 1,
      "39522": 1,
      "40828": 1,
      "41085": 1,
      "41959": 1,
      "42072": 1,
      "42582": 1,
      "42901": 1,
      "45016": 1,
      "45340": 1,
      "47202": 1,
      "48261": 1
   },
   "started": "2020-05-07T13:57:05.215Z",
   "trafficStats": {
      "incomingCompressionRatio": 0.38521256256103514,
      "incomingOctetsAppLevel": 131072000,
      "incomingOctetsWebSocketLevel": 50490581,
      "incomingOctetsWireLevel": 50494581,
      "incomingWebSocketFrames": 1000,
      "incomingWebSocketMessages": 1000,
      "incomingWebSocketOverhead": 7.922269700164472e-05,
      "outgoingCompressionRatio": 0.3932520446777344,
      "outgoingOctetsAppLevel": 131072000,
      "outgoingOctetsWebSocketLevel": 51544332,
      "outgoingOctetsWireLevel": 51950182,
      "outgoingWebSocketFrames": 50763,
      "outgoingWebSocketMessages": 1000,
      "outgoingWebSocketOverhead": 0.007873804630934008,
      "preopenIncomingOctetsWireLevel": 245,
      "preopenOutgoingOctetsWireLevel": 350
   },
   "txFrameStats": {
      "0": 49763,
      "2": 1000,
      "8": 1
   },
   "txOctetStats": {
      "7": 1,
      "8": 2,
      "10": 1,
      "11": 3,
      "13": 3,
      "14": 2,
      "15": 1,
      "16": 1,
      "17": 1,
      "18": 2,
      "19": 1,
      "20": 2,
      "21": 1,
      "23": 2,
      "25": 5,
      "27": 1,
      "33": 3,
      "34": 2,
      "35": 1,
      "38": 2,
      "43": 2,
      "46": 2,
      "49": 1,
      "52": 1,
      "53": 1,
      "55": 1,
      "56": 1,
      "57": 2,
      "58": 1,
      "59": 1,
      "60": 1,
      "62": 1,
      "65": 2,
      "66": 2,
      "67": 1,
      "68": 2,
      "69": 1,
      "70": 1,
      "71": 2,
      "73": 1,
      "74": 2,
      "75": 1,
      "76": 1,
      "77": 1,
      "78": 1,
      "79": 1,
      "80": 1,
      "81": 2,
      "82": 1,
      "83": 2,
      "84": 1,
      "85": 1,
      "86": 1,
      "87": 2,
      "88": 3,
      "89": 1,
      "90": 1,
      "92": 2,
      "93": 2,
      "94": 1,
      "95": 2,
      "98": 2,
      "101": 1,
      "104": 2,
      "105": 2,
      "106": 1,
      "110": 1,
      "111": 1,
      "112": 1,
      "113": 2,
      "114": 2,
      "116": 1,
      "119": 1,
      "120": 1,
      "121": 1,
      "122": 1,
      "123": 1,
      "124": 2,
      "126": 1,
      "127": 4,
      "128": 2,
      "129": 2,
      "131": 2,
      "134": 3,
      "135": 1,
      "137": 1,
      "138": 2,
      "139": 2,
      "141": 1,
      "143": 1,
      "144": 1,
      "145": 1,
      "146": 1,
      "147": 1,
      "149": 2,
      "150": 2,
      "151": 2,
      "153": 2,
      "154": 1,
      "155": 1,
      "157": 2,
      "158": 1,
      "159": 1,
      "160": 3,
      "161": 1,
      "162": 1,
      "164": 1,
      "165": 1,
      "166": 1,
      "167": 1,
      "170": 1,
      "171": 2,
      "172": 1,
      "174": 2,
      "175": 1,
      "176": 4,
      "177": 1,
      "179": 2,
      "180": 1,
      "183": 2,
      "185": 2,
      "186": 2,
      "187": 2,
      "188": 2,
      "189": 3,
      "190": 1,
      "192": 3,
      "194": 1,
      "195": 1,
      "196": 1,
      "198": 1,
      "200": 1,
      "201": 2,
      "203": 2,
      "204": 2,
      "205": 2,
      "206": 1,
      "207": 2,
      "208": 1,
      "210": 1,
      "211": 1,
      "212": 1,
      "213": 2,
      "214": 6,
      "215": 2,
      "216": 1,
      "217": 3,
      "218": 1,
      "220": 3,
      "221": 1,
      "222": 4,
      "223": 3,
      "225": 3,
      "226": 1,
      "227": 1,
      "228": 1,
      "229": 3,
      "231": 2,
      "232": 1,
      "234": 1,
      "235": 1,
      "236": 1,
      "237": 3,
      "238": 1,
      "239": 1,
      "241": 1,
      "242": 2,
      "247": 1,
      "248": 3,
      "249": 2,
      "250": 1,
      "251": 1,
      "252": 2,
      "253": 2,
      "255": 1,
      "258": 3,
      "267": 3,
      "272": 3,
      "273": 2,
      "274": 1,
      "276": 1,
      "280": 1,
      "281": 1,
      "283": 1,
      "285": 1,
      "289": 1,
      "290": 1,
      "292": 1,
      "308": 1,
      "309": 1,
      "315": 1,
      "324": 1,
      "327": 1,
      "329": 1,
      "333": 1,
      "335": 1,
      "343": 1,
      "350": 1,
      "355": 1,
      "357": 1,
      "361": 1,
      "362": 1,
      "368": 1,
      "370": 1,
      "373": 3,
      "379": 2,
      "380": 2,
      "382": 1,
      "385": 1,
      "394": 2,
      "396": 2,
      "399": 2,
      "404": 2,
      "415": 1,
      "418": 1,
      "422": 1,
      "429": 2,
      "438": 1,
      "441": 1,
      "452": 1,
      "456": 1,
      "457": 2,
      "458": 1,
      "461": 1,
      "471": 1,
      "476": 1,
      "483": 2,
      "491": 1,
      "492": 1,
      "501": 2,
      "503": 2,
      "504": 1,
      "508": 1,
      "512": 1,
      "518": 1,
      "521": 1,
      "522": 1,
      "523": 1,
      "525": 1,
      "526": 3,
      "527": 2,
      "528": 1,
      "531": 2,
      "532": 1,
      "533": 1,
      "535": 1,
      "537": 1,
      "538": 1,
      "543": 2,
      "544": 1,
      "545": 1,
      "548": 1,
      "552": 1,
      "555": 1,
      "560": 1,
      "563": 1,
      "567": 1,
      "569": 1,
      "572": 1,
      "573": 1,
      "577": 1,
      "583": 2,
      "589": 1,
      "594": 1,
      "595": 1,
      "597": 1,
      "599": 2,
      "603": 1,
      "611": 2,
      "620": 1,
      "621": 1,
      "624": 2,
      "626": 2,
      "627": 1,
      "629": 1,
      "631": 1,
      "633": 2,
      "634": 1,
      "638": 1,
      "639": 1,
      "641": 2,
      "644": 1,
      "647": 2,
      "648": 1,
      "649": 1,
      "652": 1,
      "653": 1,
      "655": 1,
      "662": 1,
      "664": 3,
      "665": 2,
      "666": 1,
      "667": 1,
      "669": 1,
      "670": 1,
      "671": 1,
      "672": 1,
      "673": 2,
      "675": 2,
      "676": 1,
      "677": 3,
      "678": 1,
      "681": 1,
      "683": 2,
      "687": 1,
      "688": 1,
      "689": 2,
      "690": 1,
      "693": 1,
      "694": 2,
      "696": 1,
      "697": 3,
      "698": 2,
      "699": 1,
      "700": 1,
      "701": 2,
      "702": 1,
      "703": 3,
      "704": 1,
      "705": 4,
      "706": 1,
      "707": 2,
      "709": 2,
      "711": 3,
      "712": 6,
      "713": 2,
      "714": 2,
      "715": 1,
      "716": 1,
      "717": 2,
      "719": 3,
      "720": 1,
      "721": 1,
      "722": 1,
      "723": 1,
      "724": 2,
      "725": 1,
      "726": 1,
      "727": 2,
      "728": 1,
      "730": 3,
      "731": 3,
      "734": 1,
      "735": 2,
      "736": 1,
      "737": 3,
      "738": 1,
      "739": 2,
      "740": 2,
      "741": 2,
      "742": 2,
      "743": 2,
      "744": 2,
      "745": 1,
      "747": 2,
      "748": 2,
      "749": 2,
      "752": 1,
      "753": 1,
      "756": 2,
      "757": 2,
      "758": 4,
      "759": 1,
      "760": 2,
      "761": 5,
      "762": 2,
      "763": 3,
      "764": 2,
      "766": 3,
      "767": 1,
      "768": 2,
      "769": 2,
      "770": 4,
      "771": 3,
      "772": 1,
      "773": 4,
      "774": 3,
      "775": 1,
      "776": 3,
      "777": 3,
      "778": 1,
      "779": 1,
      "780": 4,
      "781": 3,
      "783": 3,
      "784": 5,
      "785": 2,
      "787": 4,
      "788": 1,
      "789": 2,
      "790": 2,
      "791": 2,
      "792": 1,
      "793": 1,
      "794": 4,
      "795": 3,
      "796": 1,
      "797": 1,
      "799": 1,
      "800": 3,
      "801": 3,
      "803": 2,
      "804": 2,
      "805": 1,
      "806": 4,
      "807": 4,
      "808": 2,
      "809": 2,
      "810": 3,
      "811": 2,
      "812": 3,
      "813": 1,
      "815": 2,
      "816": 2,
      "817": 5,
      "818": 2,
      "819": 3,
      "821": 3,
      "822": 2,
      "823": 5,
      "824": 3,
      "826": 3,
      "827": 2,
      "828": 3,
      "829": 4,
      "830": 2,
      "831": 1,
      "832": 3,
      "833": 3,
      "834": 2,
      "835": 3,
      "836": 2,
      "838": 4,
      "839": 2,
      "840": 4,
      "841": 1,
      "843": 3,
      "844": 2,
      "845": 3,
      "846": 2,
      "847": 2,
      "848": 3,
      "849": 1,
      "850": 1,
      "852": 1,
      "853": 2,
      "854": 1,
      "855": 1,
      "857": 3,
      "858": 2,
      "860": 1,
      "862": 1,
      "863": 2,
      "864": 2,
      "865": 1,
      "866": 1,
      "867": 1,
      "868": 3,
      "869": 1,
      "870": 1,
      "872": 1,
      "873": 1,
      "875": 2,
      "877": 1,
      "878": 1,
      "879": 3,
      "881": 2,
      "882": 1,
      "886": 3,
      "887": 3,
      "888": 1,
      "889": 3,
      "890": 2,
      "894": 2,
      "895": 2,
      "896": 1,
      "897": 1,
      "898": 1,
      "899": 1,
      "901": 1,
      "903": 1,
      "904": 3,
      "908": 1,
      "910": 4,
      "911": 1,
      "913": 1,
      "917": 1,
      "918": 1,
      "919": 2,
      "920": 1,
      "921": 1,
      "922": 6,
      "924": 2,
      "926": 4,
      "927": 1,
      "929": 1,
      "930": 3,
      "931": 1,
      "932": 1,
      "933": 1,
      "934": 2,
      "935": 2,
      "936": 2,
      "937": 2,
      "938": 3,
      "940": 3,
      "941": 2,
      "942": 1,
      "943": 1,
      "947": 3,
      "949": 3,
      "950": 2,
      "952": 2,
      "957": 1,
      "958": 1,
      "962": 2,
      "964": 2,
      "965": 3,
      "966": 3,
      "967": 3,
      "969": 1,
      "970": 1,
      "971": 2,
      "972": 2,
      "973": 2,
      "974": 1,
      "975": 1,
      "977": 1,
      "979": 1,
      "981": 2,
      "982": 6,
      "987": 2,
      "989": 1,
      "990": 4,
      "991": 1,
      "992": 1,
      "993": 2,
      "994": 1,
      "995": 2,
      "996": 1,
      "997": 3,
      "999": 1,
      "1000": 1,
      "1002": 3,
      "1003": 2,
      "1004": 1,
      "1005": 1,
      "1006": 4,
      "1007": 3,
      "1008": 2,
      "1009": 4,
      "1010": 2,
      "1011": 2,
      "1012": 1,
      "1013": 2,
      "1014": 2,
      "1015": 2,
      "1016": 1,
      "1017": 4,
      "1018": 2,
      "1019": 4,
      "1021": 1,
      "1022": 1,
      "1023": 1,
      "1024": 4,
      "1025": 1,
      "1026": 1,
      "1027": 6,
      "1028": 4,
      "1029": 3,
      "1030": 3,
      "1032": 49763
   },
   "wasClean": true,
   "wasCloseHandshakeTimeout": false,
   "wasNotCleanReason": null,
   "wasOpenHandshakeTimeout": false,
   "wasServerConnectionDropTimeout": false,
   "wirelog": [
      [
         "TO",
         [
            350,
            "474554202f20485454502f312e310d0a557365722d4167656e743a204175746f6261686e5465737453756974652f302e382e302d302e31302e390d0a486f7374 ..."
         ],
         false
      ],
      [
         "RO",
         [
            245,
            "485454502f312e312031303120537769746368696e672050726f746f636f6c730d0a557067726164653a20776562736f636b65740d0a436f6e6e656374696f6e ..."
         ]
      ],
      [
         "WLM",
         false
      ],
      [
         "TI",
         480
      ],
      [
         "WLM",
         true
      ],
      [
         "TF",
         [
            2,
            "0x03e8"
         ],
         8,
         true,
         0,
         "9ce7cf9d",
         null,
         null,
         false
      ],
      [
         "TO",
         [
            8,
            "88829ce7cf9d9f0f"
         ],
         false
      ],
      [
         "RO",
         [
            4,
            "880203e8"
         ]
      ],
      [
         "RF",
         [
            2,
            "0x03e8"
         ],
         8,
         true,
         0,
         false,
         null
      ]
   ]
}